Workbook

Sheet 所需数据
A1: 员工号 | B1: 科室 | C1: 姓名 | D1: 总数 | E1: 处理最多的国家 | F1: 处理最多的数量 | G1: 三星以上 | H1: 邮件处理
A2: 182358 | B2: 航行情报室 | C2: 何萍 | D2: 230 | E2: 中国香港 | F2: 123 | G2: 24 | H2: 0
A3: 202984 | B3: 航行情报室 | C3: 刘洋 | D3: 364 | E3: 澳大利亚 | F3: 138 | G3: 53 | H3: 940
A4: 215456 | B4: 航行情报室 | C4: 刘云鹏 | D4: 268 | E4: 日本 | F4: 236 | G4: 25 | H4: 844
A5: 215448 | B5: 航行情报室 | C5: 欧阳嘉兰 | D5: 108 | E5: 日本 | F5: 86 | G5: 2 | H5: 215
A6: 240587 | B6: 航行情报室 | C6: 王康健 | D6: 2 | E6: 尼泊尔 | F6: 1 | G6: 0 | H6: 0
A7: 276401 | B7: 航行情报室 | C7: 王钰婷 | D7: 225 | E7: 比利时 | F7: 74 | G7: 21 | H7: 242
A8: 215462 | B8: 航行情报室 | C8: 吴坤林 | D8: 175 | E8: 泰国 | F8: 66 | G8: 14 | H8: 213
A9: 215454 | B9: 航行情报室 | C9: 吴奕铭 | D9: 302 | E9: 韩国 | F9: 137 | G9: 32 | H9: 303
A10: 252186 | B10: 航行情报室 | C10: 杨子城 | D10: 51 | E10: 韩国 | F10: 25 | G10: 0 | H10: 53
A11: 207803 | B11: 航行情报室 | C11: 袁伟英 | D11: 911 | E11: 法国 | F11: 232 | G11: 61 | H11: 2688
A12: 215443 | B12: 航行情报室 | C12: 张荷竞 | D12: 176 | E12: 印度 | F12: 92 | G12: 14 | H12: 606
A13: 606642 | B13: 航行情报室 | C13: 张宁 | D13: 94 | E13: 巴基斯坦 | F13: 24 | G13: 16 | H13: 62
A14: 215474 | B14: 航行情报室 | C14: 甄薇 | D14: 188 | E14: 波兰 | F14: 65 | G14: 11 | H14: 594

Sheet 统计总表
A1: 员工号 | B1: 姓名 | C1: 总数 | D1: 处理最多的国家 | E1: 处理最多的数量 | F1: 三星以上 | G1: 阿联酋 | H1: 阿塞拜疆 | I1: 爱沙尼亚 | J1: 奥地利 | K1: 澳大利亚 | L1: 巴基斯坦 | M1: 白俄罗斯 | N1: 比利时 | O1: 波兰 | P1: 丹麦 | Q1: 德国 | R1: 俄罗斯 | S1: 法国 | T1: 菲律宾 | U1: 芬兰 | V1: 格鲁吉亚 | W1: 哈萨克斯坦 | X1: 韩国 | Y1: 荷兰 | Z1: 吉尔吉斯斯坦 | AA1: 加拿大 | AB1: 柬埔寨 | AC1: 肯尼亚 | AD1: 拉脱维亚 | AE1: 老挝 | AF1: 立陶宛 | AG1: 马尔代夫 | AH1: 马来西亚 | AI1: 马里 | AJ1: 蒙古 | AK1: 孟加拉 | AL1: 缅甸 | AM1: 尼泊尔 | AN1: 日本 | AO1: 瑞典 | AP1: 斯里兰卡 | AQ1: 塔吉克斯坦 | AR1: 泰国 | AS1: 土耳其 | AT1: 乌兹别克斯坦 | AU1: 新加坡 | AV1: 新西兰 | AW1: 伊朗 | AX1: 意大利 | AY1: 印度 | AZ1: 印尼 | BA1: 英国 | BB1: 越南 | BC1: 中国澳门 | BD1: 中国台湾 | BE1: 中国香港
A2: 207803 | B2: 袁伟英 | C2: =COUNTIF(Sheet1!N:N,统计总表!B2) -> 911 | D2: =INDEX(G$1:BE$1,MATCH(E2,G2:BE2,0)) -> 法国 | E2: =MAX(G2:BE2) -> 232 | F2: 61 | G2: =COUNTIF(袁伟英!A:B,G1) -> 0 | H2: =COUNTIF(袁伟英!A:B,H1) -> 0 | I2: =COUNTIF(袁伟英!A:B,I1) -> 12 | J2: =COUNTIF(袁伟英!1:1048576,J1) -> 42 | K2: =COUNTIF(袁伟英!1:1048576,K1) -> 0 | L2: =COUNTIF(袁伟英!1:1048576,L1) -> 0 | M2: =COUNTIF(袁伟英!1:1048576,M1) -> 3 | N2: =COUNTIF(袁伟英!1:1048576,N1) -> 0 | O2: =COUNTIF(袁伟英!1:1048576,O1) -> 21 | P2: =COUNTIF(袁伟英!1:1048576,P1) -> 13 | Q2: =COUNTIF(袁伟英!1:1048576,Q1) -> 62 | ... BE2: =COUNTIF(袁伟英!1:1048576,BE1) -> 0
A3: 182358 | B3: 何萍 | C3: =COUNTIF(Sheet1!N:N,统计总表!B3) -> 230 | D3: =INDEX(G$1:BE$1,MATCH(E3,G3:BE3,0)) -> 中国香港 | E3: =MAX(G3:BE3) -> 123 | F3: 24 | G3: =COUNTIF(何萍!1:1048576,G1) -> 0 | H3: =COUNTIF(何萍!1:1048576,H1) -> 0 | I3: =COUNTIF(何萍!1:1048576,I1) -> 0 | J3: =COUNTIF(何萍!1:1048576,J1) -> 0 | K3: =COUNTIF(何萍!1:1048576,K1) -> 0 | L3: =COUNTIF(何萍!1:1048576,L1) -> 0 | M3: =COUNTIF(何萍!1:1048576,M1) -> 0 | N3: =COUNTIF(何萍!1:1048576,N1) -> 0 | ... BE3: =COUNTIF(何萍!1:1048576,BE1) -> 123
A4: 215456 | B4: 刘云鹏 | C4: =COUNTIF(Sheet1!N:N,统计总表!B4) -> 268 | D4: =INDEX(G$1:BE$1,MATCH(E4,G4:BE4,0)) -> 日本 | E4: =MAX(G4:BE4) -> 236 | F4: 25 | G4: =COUNTIF(刘云鹏!1:1048576,G1) -> 0 | H4: =COUNTIF(刘云鹏!1:1048576,H1) -> 0 | I4: =COUNTIF(刘云鹏!1:1048576,I1) -> 0 | J4: =COUNTIF(刘云鹏!1:1048576,J1) -> 0 | K4: =COUNTIF(刘云鹏!1:1048576,K1) -> 0 | L4: =COUNTIF(刘云鹏!1:1048576,L1) -> 0 | M4: =COUNTIF(刘云鹏!1:1048576,M1) -> 0 | N4: =COUNTIF(刘云鹏!1:1048576,N1) -> 0 | ... BE4: =COUNTIF(刘云鹏!1:1048576,BE1) -> 0
A5: 202984 | B5: 刘洋 | C5: =COUNTIF(Sheet1!N:N,统计总表!B5) -> 364 | D5: =INDEX(G$1:BE$1,MATCH(E5,G5:BE5,0)) -> 澳大利亚 | E5: =MAX(G5:BE5) -> 138 | F5: 53 | G5: =COUNTIF(刘洋!1:1048576,G1) -> 0 | H5: =COUNTIF(刘洋!1:1048576,H1) -> 4 | I5: =COUNTIF(刘洋!1:1048576,I1) -> 0 | J5: =COUNTIF(刘洋!1:1048576,J1) -> 0 | K5: =COUNTIF(刘洋!1:1048576,K1) -> 138 | L5: =COUNTIF(刘洋!1:1048576,L1) -> 0 | M5: =COUNTIF(刘洋!1:1048576,M1) -> 0 | N5: =COUNTIF(刘洋!1:1048576,N1) -> 0 | ... BE5: =COUNTIF(刘洋!1:1048576,BE1) -> 0
B6: 欧阳嘉兰 | C6: =COUNTIF(Sheet1!N:N,统计总表!B6) -> 108 | D6: =INDEX(G$1:BE$1,MATCH(E6,G6:BE6,0)) -> 日本 | E6: =MAX(G6:BE6) -> 86 | F6: 2 | G6: =COUNTIF(欧阳嘉兰!1:1048576,G1) -> 0 | H6: =COUNTIF(欧阳嘉兰!1:1048576,H1) -> 0 | I6: =COUNTIF(欧阳嘉兰!1:1048576,I1) -> 0 | J6: =COUNTIF(欧阳嘉兰!1:1048576,J1) -> 0 | K6: =COUNTIF(欧阳嘉兰!1:1048576,K1) -> 0 | L6: =COUNTIF(欧阳嘉兰!1:1048576,L1) -> 0 | M6: =COUNTIF(欧阳嘉兰!1:1048576,M1) -> 0 | N6: =COUNTIF(欧阳嘉兰!1:1048576,N1) -> 0 | ... BE6: =COUNTIF(欧阳嘉兰!1:1048576,BE1) -> 0
A7: 252186 | B7: 杨子城 | C7: =COUNTIF(Sheet1!N:N,统计总表!B7) -> 51 | D7: =INDEX(G$1:BE$1,MATCH(E7,G7:BE7,0)) -> 韩国 | E7: =MAX(G7:BE7) -> 25 | F7: 0 | G7: =COUNTIF(杨子城!1:1048576,G1) -> 20 | H7: =COUNTIF(杨子城!1:1048576,H1) -> 0 | I7: =COUNTIF(杨子城!1:1048576,I1) -> 0 | J7: =COUNTIF(杨子城!1:1048576,J1) -> 0 | K7: =COUNTIF(杨子城!1:1048576,K1) -> 0 | L7: =COUNTIF(杨子城!1:1048576,L1) -> 0 | M7: =COUNTIF(杨子城!1:1048576,M1) -> 0 | N7: =COUNTIF(杨子城!1:1048576,N1) -> 0 | ... BE7: =COUNTIF(杨子城!1:1048576,BE1) -> 0
A8: 276401 | B8: 王钰婷 | C8: =COUNTIF(Sheet1!N:N,统计总表!B8) -> 225 | D8: =INDEX(G$1:BE$1,MATCH(E8,G8:BE8,0)) -> 比利时 | E8: =MAX(G8:BE8) -> 74 | F8: 21 | G8: =COUNTIF(王钰婷!1:1048576,G1) -> 0 | H8: =COUNTIF(王钰婷!1:1048576,H1) -> 0 | I8: =COUNTIF(王钰婷!1:1048576,I1) -> 0 | J8: =COUNTIF(王钰婷!1:1048576,J1) -> 0 | K8: =COUNTIF(王钰婷!1:1048576,K1) -> 0 | L8: =COUNTIF(王钰婷!1:1048576,L1) -> 0 | M8: =COUNTIF(王钰婷!1:1048576,M1) -> 0 | N8: =COUNTIF(王钰婷!1:1048576,N1) -> 74 | ... BE8: =COUNTIF(王钰婷!1:1048576,BE1) -> 0
B9: 吴坤林 | C9: =COUNTIF(Sheet1!N:N,统计总表!B9) -> 175 | D9: =INDEX(G$1:BE$1,MATCH(E9,G9:BE9,0)) -> 泰国 | E9: =MAX(G9:BE9) -> 66 | F9: 14 | G9: =COUNTIF(吴坤林!1:1048576,G1) -> 0 | H9: =COUNTIF(吴坤林!1:1048576,H1) -> 0 | I9: =COUNTIF(吴坤林!1:1048576,I1) -> 0 | J9: =COUNTIF(吴坤林!1:1048576,J1) -> 0 | K9: =COUNTIF(吴坤林!1:1048576,K1) -> 0 | L9: =COUNTIF(吴坤林!1:1048576,L1) -> 0 | M9: =COUNTIF(吴坤林!1:1048576,M1) -> 0 | N9: =COUNTIF(吴坤林!1:1048576,N1) -> 0 | ... BE9: =COUNTIF(吴坤林!1:1048576,BE1) -> 0
B10: 吴奕铭 | C10: =COUNTIF(Sheet1!N:N,统计总表!B10) -> 302 | D10: =INDEX(G$1:BE$1,MATCH(E10,G10:BE10,0)) -> 韩国 | E10: =MAX(G10:BE10) -> 137 | F10: 32 | G10: =COUNTIF(吴奕铭!1:1048576,G1) -> 101 | H10: =COUNTIF(吴奕铭!1:1048576,H1) -> 0 | I10: =COUNTIF(吴奕铭!1:1048576,I1) -> 0 | J10: =COUNTIF(吴奕铭!1:1048576,J1) -> 0 | K10: =COUNTIF(吴奕铭!1:1048576,K1) -> 0 | L10: =COUNTIF(吴奕铭!1:1048576,L1) -> 0 | M10: =COUNTIF(吴奕铭!1:1048576,M1) -> 0 | N10: =COUNTIF(吴奕铭!1:1048576,N1) -> 0 | ... BE10: =COUNTIF(吴奕铭!1:1048576,BE1) -> 0
B11: 王康健 | C11: =COUNTIF(Sheet1!N:N,统计总表!B11) -> 2 | D11: =INDEX(G$1:BE$1,MATCH(E11,G11:BE11,0)) -> 尼泊尔 | E11: =MAX(G11:BE11) -> 1 | F11: 0 | G11: =COUNTIF(王康健!1:1048576,G1) -> 0 | H11: =COUNTIF(王康健!1:1048576,H1) -> 0 | I11: =COUNTIF(王康健!1:1048576,I1) -> 0 | J11: =COUNTIF(王康健!1:1048576,J1) -> 0 | K11: =COUNTIF(王康健!1:1048576,K1) -> 0 | L11: =COUNTIF(王康健!1:1048576,L1) -> 0 | M11: =COUNTIF(王康健!1:1048576,M1) -> 0 | N11: =COUNTIF(王康健!1:1048576,N1) -> 0 | ... BE11: =COUNTIF(王康健!1:1048576,BE1) -> 0
A12: 215443 | B12: 张荷竞 | C12: =COUNTIF(Sheet1!N:N,统计总表!B12) -> 176 | D12: =INDEX(G$1:BE$1,MATCH(E12,G12:BE12,0)) -> 印度 | E12: =MAX(G12:BE12) -> 92 | F12: 14 | G12: =COUNTIF(张荷竞!1:1048576,G1) -> 0 | H12: =COUNTIF(张荷竞!1:1048576,H1) -> 0 | I12: =COUNTIF(张荷竞!1:1048576,I1) -> 0 | J12: =COUNTIF(张荷竞!1:1048576,J1) -> 0 | K12: =COUNTIF(张荷竞!1:1048576,K1) -> 0 | L12: =COUNTIF(张荷竞!1:1048576,L1) -> 37 | M12: =COUNTIF(张荷竞!1:1048576,M1) -> 0 | N12: =COUNTIF(张荷竞!1:1048576,N1) -> 0 | ... BE12: =COUNTIF(张荷竞!1:1048576,BE1) -> 0
A13: 215474 | B13: 甄薇 | C13: =COUNTIF(Sheet1!N:N,统计总表!B13) -> 188 | D13: =INDEX(G$1:BE$1,MATCH(E13,G13:BE13,0)) -> 波兰 | E13: =MAX(G13:BE13) -> 65 | F13: 11 | G13: =COUNTIF(甄薇!1:1048576,G1) -> 0 | H13: =COUNTIF(甄薇!1:1048576,H1) -> 0 | I13: =COUNTIF(甄薇!1:1048576,I1) -> 9 | J13: =COUNTIF(甄薇!1:1048576,J1) -> 0 | K13: =COUNTIF(甄薇!1:1048576,K1) -> 0 | L13: =COUNTIF(甄薇!1:1048576,L1) -> 0 | M13: =COUNTIF(甄薇!1:1048576,M1) -> 4 | N13: =COUNTIF(甄薇!1:1048576,N1) -> 0 | ... BE13: =COUNTIF(甄薇!1:1048576,BE1) -> 0
A14: 606642 | B14: 张宁 | C14: =COUNTIF(Sheet1!N:N,统计总表!B14) -> 94 | D14: =INDEX(G$1:BE$1,MATCH(E14,G14:BE14,0)) -> 巴基斯坦 | E14: =MAX(G14:BE14) -> 24 | F14: 16 | G14: =COUNTIF(张宁!1:1048576,G1) -> 0 | H14: =COUNTIF(张宁!1:1048576,H1) -> 0 | I14: =COUNTIF(张宁!1:1048576,I1) -> 0 | J14: =COUNTIF(张宁!1:1048576,J1) -> 0 | K14: =COUNTIF(张宁!1:1048576,K1) -> 0 | L14: =COUNTIF(张宁!1:1048576,L1) -> 24 | M14: =COUNTIF(张宁!1:1048576,M1) -> 0 | N14: =COUNTIF(张宁!1:1048576,N1) -> 0 | ... BE14: =COUNTIF(张宁!1:1048576,BE1) -> 2
C15: =SUM(C2:C14) -> 3094 | G15: =SUM(G2:G14) -> 121 | H15: =SUM(H2:H14) -> 4 | I15: =SUM(I2:I14) -> 21 | J15: =SUM(J2:J14) -> 42 | K15: =SUM(K2:K14) -> 138 | L15: =SUM(L2:L14) -> 61 | M15: =SUM(M2:M14) -> 7 | N15: =SUM(N2:N14) -> 74 | ... BE15: =SUM(BE2:BE14) -> 125
G16: 三星以上
G17: =COUNTIF(三星以上!1:1048576,G1) -> 8 | H17: =COUNTIF(三星以上!1:1048576,H1) -> 0 | I17: =COUNTIF(三星以上!1:1048576,I1) -> 1 | J17: =COUNTIF(三星以上!1:1048576,J1) -> 3 | K17: =COUNTIF(三星以上!1:1048576,K1) -> 25 | L17: =COUNTIF(三星以上!1:1048576,L1) -> 4 | M17: =COUNTIF(三星以上!1:1048576,M1) -> 1 | N17: =COUNTIF(三星以上!1:1048576,N1) -> 5 | ... BE17: =COUNTIF(三星以上!1:1048576,BE1) -> 25

Sheet Sheet1
A1: id | B1: period | C1: countryName | D1: title | E1: modifiedParts | F1: type | G1: content | H1: deptIds | I1: dept | J1: effDt | K1: expDt | L1: analyzeResult | M1: createStaff | N1: staffName | O1: operatorName | P1: createTime | Q1: showPath | R1: flowStatus | S1: relatedFileid | T1: operTime | U1: sendEmail | V1: effDtType | W1: expDtType | X1: attention | Y1: airInfluence | Z1: flowInfoId
A2: 537 | B2: 202102 | C2: 法国 | D2: 修订BREST UAC高空管制区域的无线通信设备信息 | E2: AMDT A 02/21 GEN3.4-55 | F2: 19 | G2: 20210208d45b8e1d-b743-4331-8b6d-65dec621507b.txt | H2: 1,12,15,16,17 | I2: 飞行总队,运指航务,运指调度,运指签派 | J2: 2021-02-25 00:00 | K2: 2999-12-31 00:00 | L2: 请相关部门了解 | M2: 207803 | N2: 袁伟英 | O2: 袁伟英 | P2: 2021-02-08 14:28 | Q2: /全球AIP/欧洲/法国/AMDT | R2: Y | T2: 2021-02-09 13:17 | U2: N | Z2: 597
A3: 539 | B3: 202102 | C3: 法国 | D3: 修订管制区域的水平、垂直范围信息 | E3: AMDT A 02/21 ENR2.2-15 | F3: 19 | G3: 2021020832f75169-7b57-4396-8ff2-63ca1eec965d.txt | H3: 1,12 | I3: 飞行总队 | J3: 2021-02-25 00:00 | K3: 2999-12-31 00:00 | L3: 请相关部门了解 | M3: 207803 | N3: 袁伟英 | O3: 袁伟英 | P3: 2021-02-08 14:55 | Q3: /全球AIP/欧洲/法国/AMDT | R3: Y | T3: 2021-02-09 13:17 | U3: N | Z3: 599
A4: 549 | B4: 202102 | C4: 意大利 | D4: LIEO机场发布施工计划 | E4: SUP 01/21 | F4: 27 | G4: 20210209136f853c-13a6-46ec-aa9c-df854f721db9.txt | J4: 2021-03-25 00:00 | K4: 2021-07-14 00:00 | L4: 无影响 | M4: 207803 | N4: 袁伟英 | O4: 袁伟英 | P4: 2021-02-09 12:40 | Q4: /全球AIP/欧洲/意大利/SUP | R4: Y | S4: 458537 | T4: 2021-02-09 13:12 | U4: N | Z4: 609
A5: 550 | B5: 202102 | C5: 意大利 | D5: LICC机场发布施工计划 | E5: SUP 03/21 | F5: 27 | G5: 2021020922a9001b-648b-4aea-9e98-58b97a851d47.txt | J5: 2021-04-01 00:00 | K5: 2021-09-30 00:00 | L5: 无影响 | M5: 207803 | N5: 袁伟英 | O5: 袁伟英 | P5: 2021-02-09 12:43 | Q5: /全球AIP/欧洲/意大利/SUP | R5: Y | S5: 458539 | T5: 2021-02-09 13:12 | U5: N | Z5: 610
A6: 552 | B6: 202102 | C6: 法国 | D6: 在机场LFOJ建立实验性的无线电和应答机强制区域 | E6: SUP 14/21 | F6: 3 | G6: 20210209d80af11f-9e99-4b46-8008-c08f45008fbf.txt | J6: 2021-02-18 00:00 | K6: 2021-04-21 00:00 | L6: 无影响 | M6: 207803 | N6: 袁伟英 | O6: 袁伟英 | P6: 2021-02-09 12:58 | Q6: /全球AIP/欧洲/法国/SUP | R6: Y | S6: 458542 | T6: 2021-02-09 13:11 | U6: N | Z6: 612
A7: 553 | B7: 202102 | C7: 法国 | D7: 临时限制区的建立 | E7: SUP 15/21 | F7: 16 | G7: 202102098da7328b-4581-478a-94d9-96485848a794.txt | J7: 2021-02-22 00:00 | K7: 2021-02-26 00:00 | L7: 经系统检查，无影响 | M7: 207803 | N7: 袁伟英 | O7: 袁伟英 | P7: 2021-02-09 13:01 | Q7: /全球AIP/欧洲/法国/SUP | R7: Y | S7: 458543 | T7: 2021-02-09 13:11 | U7: N | Z7: 613
A8: 554 | B8: 202102 | C8: 印度 | D8: 关于通过数字天空平台在印度领空允许操作区域远程驾驶飞机的信息 | E8: SUP25/21 | F8: 10 | G8: 202102094b84eb22-f8db-4e56-9961-dc7123a4c011.txt | J8: 2021-02-05 00:00 | K8: 2999-12-31 00:00 | M8: 215443 | N8: 张荷竞 | O8: 袁伟英 | P8: 2021-02-09 14:29 | Q8: /全球AIP/亚洲/印度/SUP | R8: Y | S8: 458544 | T8: 2021-02-10 14:59 | U8: N | Z8: 614
A9: 556 | B9: 202102 | C9: 澳大利亚 | D9: YSTW机场地面灯光替换 | E9: AIC H05/21 | F9: 27 | G9: 2021020979bb8b05-cee7-450d-a5d0-f9dbeed8773d.txt | H9: 12 | J9: 2021-02-28 00:00 | K9: 2999-12-31 00:00 | L9: 暂无影响 | M9: 202984 | N9: 刘洋 | O9: 袁伟英 | P9: 2021-02-09 14:54 | Q9: /全球AIP/大洋洲/澳大利亚/AIC/2021 | R9: Y | S9: 458546 | T9: 2021-02-10 14:59 | U9: N | Z9: 616
A10: 557 | B10: 202102 | C10: 英国 | D10: EGPH机场区域新增障碍物信息 | E10: SUP 07/21 | F10: 24 | G10: 202102101c0b0f1d-be26-4e12-ad76-6a5062ffb4cd.txt | J10: 2021-02-11 00:00 | K10: 2021-09-01 00:00 | L10: 无影响 | M10: 207803 | N10: 袁伟英 | O10: 袁伟英 | P10: 2021-02-10 15:37 | Q10: /全球AIP/欧洲/英国/SUP | R10: Y | S10: 459663 | T10: 2021-02-10 15:58 | U10: N | Z10: 617
A11: 559 | B11: 202102 | C11: 英国 | D11: 英国SUP校核单 | E11: SUP 09/21 | F11: 6 | G11: 202102100df3b3d1-9471-4849-b763-0a13ff595f11.txt | J11: 2021-02-11 00:00 | K11: 2999-12-31 00:00 | L11: 英国SUP 校核单简单了解，暂无影响 | M11: 207803 | N11: 袁伟英 | O11: 袁伟英 | P11: 2021-02-10 16:01 | Q11: /全球AIP/欧洲/英国/SUP | R11: Y | S11: 459665 | T11: 2021-02-10 16:01 | U11: N | Z11: 619
A12: 560 | B12: 202102 | C12: 英国 | D12: 公布英国最新AIC校核单 | E12: AIC W004/21 | F12: 6 | G12: 20210210ea556e9d-1792-4ef6-ab3c-28138bb6e576.txt | J12: 2021-02-11 00:00 | K12: 2999-12-31 00:00 | L12: 暂无影响 | M12: 207803 | N12: 袁伟英 | O12: 袁伟英 | P12: 2021-02-10 16:06 | Q12: /全球AIP/欧洲/英国/AIC | R12: Y | S12: 459666 | T12: 2021-02-10 17:04 | U12: N | Z12: 620
A13: 561 | B13: 202102 | C13: 英国 | D13: 公布EGTH机场信息及2021年特殊事件 | E13: AIC Y002/21 | F13: 29 | G13: 2021021055765676-427c-4f83-8a10-67a11fb4a0b6.txt | J13: 2021-02-11 00:00 | K13: 2999-12-31 00:00 | L13: 非监控航点，无影响 | M13: 207803 | N13: 袁伟英 | O13: 袁伟英 | P13: 2021-02-10 16:13 | Q13: /全球AIP/欧洲/英国/AIC | R13: Y | S13: 459667 | T13: 2021-02-10 17:04 | U13: N | Z13: 621
A14: 562 | B14: 202102 | C14: 英国 | D14: 因军演对部分区域进行GPS信号干扰测试 | E14: AIC Y003/21 | F14: 19 | G14: 2021021071581298-04b7-4033-8d6b-0afb9d38a656.txt | J14: 2021-02-21 00:00 | K14: 2021-04-09 00:00 | L14: 暂无影响 | M14: 207803 | N14: 袁伟英 | O14: 袁伟英 | P14: 2021-02-10 16:52 | Q14: /全球AIP/欧洲/英国/AIC | R14: Y | S14: 459668 | T14: 2021-02-10 16:52 | U14: N | Z14: 622
A15: 564 | B15: 202102 | C15: 韩国 | D15: RKPU机场临时障碍物修正 | E15: AIP SUP 03/21 | F15: 24 | G15: 20210210feeec771-198a-4a81-b96d-e8093b00e810.txt | J15: 2020-12-31 00:00 | K15: 2021-05-31 15:00 | L15: 暂无影响 | M15: 207803 | N15: 袁伟英 | O15: 袁伟英 | P15: 2021-02-10 17:37 | Q15: /全球AIP/亚洲/韩国/AIC/2021 | R15: Y | S15: 459670 | T15: 2021-02-10 17:38 | U15: N | Z15: 624
A16: 567 | B16: 202102 | C16: 澳大利亚 | D16: YOLD机场修订RNAV(GNSS)07/25进近程序 | E16: SUP H25/21 | F16: 5,32 | G16: 20210211f0adeef0-2f57-438e-9992-e79e37b4ae0c.txt | H16: 12,17 | I16: 运指签派 | J16: 2021-02-20 02:00 | K16: 2999-12-31 00:00 | L16: 暂无影响 | M16: 202984 | N16: 刘洋 | O16: 袁伟英 | P16: 2021-02-11 18:26 | Q16: /全球AIP/大洋洲/澳大利亚/SUP/2021 | R16: Y | S16: 459673 | T16: 2021-02-16 10:18 | U16: N | Z16: 627
A17: 568 | B17: 202102 | C17: 澳大利亚 | D17: YOLD机场修订ERSA机场信息和RDS跑道长度 | E17: SUP H27/21 | F17: 4 | G17: 202102114e8ad1b9-63e0-48cb-b865-8e29596dc8e0.txt | H17: 12,17 | I17: 运指签派 | J17: 2021-02-20 02:00 | K17: 2999-12-31 00:00 | L17: 暂无影响 | M17: 202984 | N17: 刘洋 | O17: 袁伟英 | P17: 2021-02-11 19:41 | Q17: /全球AIP/大洋洲/澳大利亚/SUP/2021 | R17: Y | S17: 459674 | T17: 2021-02-16 10:18 | U17: N | Z17: 628
A18: 575 | B18: 202102 | C18: 日本 | D18: 福岛机场新增直升机程序 | E18: RJ SUP 002/21 | F18: 29 | G18: 20210212f4ce3373-e845-4630-be18-32023933e7d5.txt | J18: 2021-02-25 00:00 | K18: 2999-12-31 00:00 | L18: 对公司运行无影响。 | M18: 215456 | N18: 刘云鹏 | O18: 刘云鹏 | P18: 2021-02-12 16:42 | Q18: /全球AIP/亚洲/日本/SUP/2021 | R18: Y | S18: 459010 | T18: 2021-02-12 20:05 | U18: N | Z18: 635
A19: 578 | B19: 202102 | C19: 日本 | D19: 日本释放观测气球 | E19: RJ SUP 005/21 | F19: 29 | G19: 20210212591fb460-bb74-436d-8b0f-c611f3a97a65.txt | J19: 2021-02-25 00:00 | K19: 2999-12-31 00:00 | L19: 无影响。 | M19: 215456 | N19: 刘云鹏 | O19: 刘云鹏 | P19: 2021-02-12 19:02 | Q19: /全球AIP/亚洲/日本/SUP/2021 | R19: Y | S19: 459013 | T19: 2021-02-12 20:05 | U19: N | Z19: 638
A20: 579 | B20: 202102 | C20: 日本 | D20: 航空自卫队演习 | E20: RJ SUP 006/21 | F20: 16 | G20: 20210212aac97d45-422e-419e-8e24-f9ff865062cf.txt | J20: 2021-02-25 00:00 | K20: 2999-12-31 00:00 | M20: 215456 | N20: 刘云鹏 | O20: 刘云鹏 | P20: 2021-02-12 19:07 | Q20: /全球AIP/亚洲/日本/SUP/2021 | R20: Y | S20: 459014 | T20: 2021-02-12 20:05 | U20: N | Z20: 639
A21: 580 | B21: 202102 | C21: 日本 | D21: RJKA机场程序修订 | E21: RJ SUP 007/21 | F21: 21 | G21: 2021021260938359-a3fc-44b8-a852-025e285e8720.txt | J21: 2021-02-25 00:00 | K21: 2999-12-31 00:00 | L21: 非南航航点，暂无影响 | M21: 215456 | N21: 刘云鹏 | O21: 刘云鹏 | P21: 2021-02-12 19:13 | Q21: /全球AIP/亚洲/日本/SUP/2021 | R21: Y | S21: 459015 | T21: 2021-02-12 20:05 | U21: N | Z21: 640
A22: 581 | B22: 202102 | C22: 日本 | D22: 日本松山机场新增运行限制 | E22: RJ SUP 008/21 | F22: 26 | G22: 20210212e2125ced-0356-4af7-b22f-32b4cb97649a.txt | J22: 2021-02-25 00:00 | K22: 2999-12-31 00:00 | L22: 非南航航点，无影响。 | M22: 215456 | N22: 刘云鹏 | O22: 刘云鹏 | P22: 2021-02-12 19:16 | Q22: /全球AIP/亚洲/日本/SUP/2021 | R22: Y | S22: 459016 | T22: 2021-02-12 20:05 | U22: N | Z22: 641
A23: 583 | B23: 202102 | C23: 日本 | D23: 福冈机场障碍物信息更新 | E23: RJ SUP 010/21 | F23: 24 | G23: 20210212528615a2-6a16-4e50-976e-fb57dcace719.txt | J23: 2021-02-25 00:00 | K23: 2999-12-31 00:00 | L23: 请性能评估，请飞行机组注意。 | M23: 215456 | N23: 刘云鹏 | O23: 刘云鹏 | P23: 2021-02-12 19:26 | Q23: /全球AIP/亚洲/日本/SUP/2021 | R23: Y | S23: 459018 | T23: 2021-02-12 20:05 | U23: N | Z23: 643
A24: 586 | B24: 202102 | C24: 法国 | D24: 法国颁布本国领土以外的飞越易冲突地区 | E24: AIC A 02/21 | F24: 7,10 | G24: 20210216fef975ad-d7c4-425a-8b92-471ebb78811f.txt | H24: 1,12,16,17 | I24: 飞行总队,运指调度,运指签派 | J24: 2021-02-11 00:00 | K24: 2999-12-31 00:00 | L24: 属南航运行区域，法国当局的规定，简单了解 | M24: 207803 | N24: 袁伟英 | O24: 袁伟英 | P24: 2021-02-16 10:49 | Q24: /全球AIP/欧洲/法国/AIC | R24: Y | S24: 459677 | T24: 2021-02-16 14:28 | U24: N | Z24: 646
A25: 587 | B25: 202102 | C25: 法国 | D25: 划设16个限制区供无人机飞行 | E25: SUP 16/21 | F25: 16 | G25: 2021021668004491-168f-4c12-8c51-e9db1dbc3d7a.txt | J25: 2021-02-25 00:00 | K25: 2021-08-18 00:00 | L25: 经检查，无影响 | M25: 207803 | N25: 袁伟英 | O25: 袁伟英 | P25: 2021-02-16 11:08 | Q25: /全球AIP/欧洲/法国/SUP | R25: Y | S25: 459678 | T25: 2021-02-16 14:28 | U25: N | Z25: 647
A26: 588 | B26: 202102 | C26: 法国 | D26: 评估Alsace 平原各医院间的直升机IFR航路 | E26: SUP 017/21 | F26: 15 | G26: 202102163d2b8341-accf-4e69-ba00-fe21d7190bed.txt | J26: 2021-03-25 00:00 | K26: 2021-04-22 00:00 | L26: 暂无影响 | M26: 207803 | N26: 袁伟英 | O26: 袁伟英 | P26: 2021-02-16 11:12 | Q26: /全球AIP/欧洲/法国/SUP | R26: Y | S26: 459679 | T26: 2021-02-16 14:28 | U26: N | Z26: 648
A27: 590 | B27: 202102 | C27: 法国 | D27: 建立危险区D300对应的飞行计划缓冲区 | E27: SUP A 19/21 | F27: 16 | G27: 2021021648f79303-3d39-41e9-bcd0-d6b882e3373a.txt | J27: 2021-03-26 00:00 | K27: 2021-12-01 00:00 | L27: 无影响 | M27: 207803 | N27: 袁伟英 | O27: 袁伟英 | P27: 2021-02-16 11:41 | Q27: /全球AIP/欧洲/法国/SUP | R27: Y | S27: 459681 | T27: 2021-02-16 14:27 | U27: N | Z27: 650
A28: 591 | B28: 202102 | C28: 法国 | D28: 关于直升飞机运行RNP261 Pins IFR程序的运行评估 | E28: SUP 20/21 | F28: 6 | G28: 20210216db3db394-6d0e-487e-a8b9-b3df96256fc1.txt | J28: 2021-03-25 00:00 | K28: 2021-04-20 00:00 | L28: 暂无影响 | M28: 207803 | N28: 袁伟英 | O28: 袁伟英 | P28: 2021-02-16 11:45 | Q28: /全球AIP/欧洲/法国/SUP | R28: Y | S28: 459682 | T28: 2021-02-16 14:27 | U28: N | Z28: 651
A29: 593 | B29: 202102 | C29: 法国 | D29: 因BELOTE 2021-02军演建立临时限制区危险区 | E29: SUP 22/21 | F29: 17 | G29: 202102161594aaa3-4f14-49db-9934-bec565453883.txt | J29: 2021-03-02 00:00 | K29: 2021-03-04 00:00 | L29: 无影响 | M29: 207803 | N29: 袁伟英 | O29: 袁伟英 | P29: 2021-02-16 12:04 | Q29: /全球AIP/欧洲/法国/SUP | R29: Y | S29: 459684 | T29: 2021-02-16 14:26 | U29: N | Z29: 653
A30: 595 | B30: 202102 | C30: 法国 | D30: 建立临时限制区 | E30: SUP 024/21 | F30: 16 | G30: 20210216c41ea0ad-0509-4d46-855f-2d31fa5601bb.txt | J30: 2021-03-01 00:00 | K30: 2021-08-13 00:00 | L30: 无影响 | M30: 207803 | N30: 袁伟英 | O30: 袁伟英 | P30: 2021-02-16 12:19 | Q30: /全球AIP/欧洲/法国/SUP | R30: Y | S30: 459686 | T30: 2021-02-16 14:25 | U30: N | Z30: 655
A31: 596 | B31: 202102 | C31: 芬兰 | D31: 芬兰建立临时限制区 | E31: SUP 06/21 | F31: 16 | G31: 2021021615fec0e0-4b7e-4d70-b345-3d75eb414201.txt | J31: 2021-02-23 07:00 | K31: 2021-02-25 14:30 | L31: 已检查，暂无影响 | M31: 207803 | N31: 袁伟英 | O31: 袁伟英 | P31: 2021-02-16 14:15 | Q31: /全球AIP/欧洲/芬兰/SUP | R31: Y | S31: 459689 | T31: 2021-02-16 14:25 | U31: N | Z31: 656
A32: 597 | B32: 202102 | C32: 芬兰 | D32: 芬兰建立临时危险区 | E32: SUP 07/21 | F32: 16 | G32: 20210216b571527a-30b5-4bac-af94-f0f280a35739.txt | J32: 2021-02-26 10:00 | K32: 2021-02-28 18:00 | L32: 芬兰属公司航路飞越地区，低高度限制区，暂无影响 | M32: 207803 | N32: 袁伟英 | O32: 袁伟英 | P32: 2021-02-16 14:25 | Q32: /全球AIP/欧洲/芬兰/SUP | R32: Y | S32: 459690 | T32: 2021-02-16 14:25 | U32: N | Z32: 657
A33: 598 | B33: 202102 | C33: 澳大利亚 | D33: YIBO机场新增进近程序 | E33: AIRAC SUP H29/21 | F33: 5,32 | G33: 202102173e925f20-f919-4541-a3c1-d620c3590b4c.txt | H33: 12 | J33: 2021-04-21 00:00 | K33: 2999-12-31 00:00 | L33: 暂无影响 | M33: 202984 | N33: 刘洋 | O33: 袁伟英 | P33: 2021-02-17 10:28 | Q33: /全球AIP/大洋洲/澳大利亚/SUP/2021 | R33: Y | S33: 459691 | T33: 2021-02-18 09:23 | U33: N | Z33: 658
A34: 599 | B34: 202102 | C34: 澳大利亚 | D34: YWLM机场在管制空域以下目视进近意外下降风险 | E34: AIC H06/21 | F34: 26 | G34: 2021021703f0a9ff-b75e-4f4b-9042-6b900c702cde.txt | H34: 12 | J34: 2021-02-16 00:00 | K34: 2022-03-01 10:53 | L34: 暂无影响 | M34: 202984 | N34: 刘洋 | O34: 袁伟英 | P34: 2021-02-17 10:54 | Q34: /全球AIP/大洋洲/澳大利亚/AIC/2021 | R34: Y | S34: 459692 | T34: 2021-02-18 09:23 | U34: N | Z34: 659
A35: 601 | B35: 202102 | C35: 越南 | D35: 越南VVDN岘港机场修改跑道相关参数、障碍物信息等 | E35: AIP SUP A06/21 | F35: 20,24,29 | G35: 2021022005b95636-130d-4a6c-b912-17aa9209b9c8.txt | H35: 1,12,14,17 | I35: 飞行总队,运指性能,运指签派 | J35: 2021-03-25 00:00 | K35: 2999-12-31 00:00 | L35: 对运行有影响，相关部门需要关注。 | M35: 215462 | N35: 吴坤林 | O35: 袁伟英 | P35: 2021-02-18 09:31 | Q35: /全球AIP/亚洲/越南/SUP | R35: Y | S35: 459707 | T35: 2021-02-27 10:29 | U35: N | Z35: 661
A36: 602 | B36: 202102 | C36: 印度 | D36: AIC校核单 | E36: AIC01/21 | F36: 6 | G36: 20210218775c8155-0795-45ff-b57d-5b77f8c7d5cc.txt | H36: 12 | J36: 2021-01-08 00:00 | K36: 2999-12-31 00:00 | M36: 215443 | N36: 张荷竞 | O36: 袁伟英 | P36: 2021-02-18 09:38 | Q36: /全球AIP/亚洲/印度/AIC | R36: Y | S36: 459712 | T36: 2021-02-20 16:44 | U36: N | Z36: 662
A37: 603 | B37: 202102 | C37: 中国台湾 | D37: RCTP机场修订滑行道道面及强度 | E37: 台湾AIP AMDT02/21(AD 2 RCTP-3、4) | F37: 22,29 | G37: 2021021897820687-98d8-457d-ba77-595db603ece9.txt | H37: 1,12,17 | I37: 飞行总队,运指签派 | J37: 2021-03-11 00:00 | K37: 2999-12-31 00:00 | L37: 对地面运行有影响，请相关部门注意 | M37: 182358 | N37: 何萍 | O37: 袁伟英 | P37: 2021-02-18 09:48 | Q37: /全球AIP/亚洲/中国台湾/AMDT | R37: Y | S37: 459711 | T37: 2021-02-20 16:49 | U37: N | Z37: 663
A38: 604 | B38: 202102 | C38: 印度 | D38: VIDP第三次管制期航空关税事宜 | E38: AIC06/21 | F38: 1 | G38: 202102186a16c53d-946a-4820-9ce2-c199b5ab2901.txt | H38: 12 | J38: 2021-01-12 00:00 | K38: 2999-12-31 00:00 | M38: 215443 | N38: 张荷竞 | O38: 袁伟英 | P38: 2021-02-18 09:50 | Q38: /全球AIP/亚洲/印度/AIC | R38: Y | S38: 459713 | T38: 2021-02-20 16:44 | U38: N | Z38: 664
A39: 605 | B39: 202102 | C39: 印度 | D39: VOTV机场停机位及滑行路线试运行 | E39: SUP 26/21 | F39: 23 | G39: 202102185c0f33fa-ff45-48cc-8d2a-65c710d04be9.txt | J39: 2021-02-05 00:00 | K39: 2999-12-31 00:00 | M39: 215443 | N39: 张荷竞 | O39: 袁伟英 | P39: 2021-02-18 09:57 | Q39: /全球AIP/亚洲/印度/SUP | R39: Y | S39: 459714 | T39: 2021-02-20 16:44 | U39: N | Z39: 665
A40: 607 | B40: 202102 | C40: 印度 | D40: VOHY机场数据 | E40: SUP 27/21 | F40: 4 | G40: 202102185b8b1b25-c8d6-465d-9f7c-1475b8b239d9.txt | J40: 2021-02-05 00:00 | K40: 2999-12-31 00:00 | M40: 215443 | N40: 张荷竞 | O40: 袁伟英 | P40: 2021-02-18 10:01 | Q40: /全球AIP/亚洲/印度/SUP | R40: Y | S40: 459715 | T40: 2021-02-20 16:42 | U40: N | Z40: 667
A41: 608 | B41: 202102 | C41: 中国台湾 | D41: 区域导航(RNAV)航路 | E41: 台湾AIP AMDT02/21（ENR3.3-1） | F41: 10 | G41: 20210218c339ae13-8882-4b3f-956e-7c34ad9d7983.txt | H41: 1,12,17 | I41: 飞行总队,运指签派 | J41: 2021-03-11 00:00 | K41: 2999-12-31 00:00 | L41: 对运行有影响，请相关部门注意 | M41: 182358 | N41: 何萍 | O41: 袁伟英 | P41: 2021-02-18 10:01 | Q41: /全球AIP/亚洲/中国台湾/AMDT | R41: Y | T41: 2021-02-20 16:49 | U41: N | Z41: 668
A42: 609 | B42: 202102 | C42: 德国 | D42: 德国AIC校核单 | E42: AIC 02/21 | F42: 6 | G42: 202102180a9927c2-8eba-42a8-aa3e-db2e9f70acc6.txt | J42: 2021-02-25 00:00 | K42: 2999-12-31 00:00 | L42: 暂无影响 | M42: 207803 | N42: 袁伟英 | O42: 袁伟英 | P42: 2021-02-18 10:02 | Q42: /全球AIP/欧洲/德国/AIC | R42: Y | S42: 459716 | T42: 2021-02-20 16:42 | U42: N | Z42: 669
A43: 611 | B43: 202102 | C43: 印度 | D43: VIDP1号航站楼E2滑行道部分重新指定及803停机位试运行 | E43: SUP 28/21 | F43: 22,23 | G43: 20210218be7d9709-48a1-46b7-abe9-15e7890ecf03.txt | H43: 1,12,17 | I43: 飞行总队,运指签派 | J43: 2021-03-25 00:00 | K43: 2999-12-31 00:00 | L43: VIDP机场滑行道重新指定以及新停机位试运行 | M43: 215443 | N43: 张荷竞 | O43: 袁伟英 | P43: 2021-02-18 10:19 | Q43: /全球AIP/亚洲/印度/SUP | R43: Y | S43: 459718 | T43: 2021-02-27 10:32 | U43: N | Z43: 671
A44: 613 | B44: 202102 | C44: 拉脱维亚 | D44: 修改航空事件汇报的联系信息 | E44: SUP 2/21 | F44: 6 | G44: 202102181d88331b-e5ae-44f0-a0ca-f3d05926127c.txt | J44: 2021-02-12 00:00 | K44: 2021-03-19 23:59 | L44: 暂无影响。 | M44: 215474 | N44: 甄薇 | O44: 袁伟英 | P44: 2021-02-18 10:22 | Q44: /全球AIP/欧洲/拉脱维亚/SUP | R44: Y | S44: 459719 | T44: 2021-02-20 16:45 | U44: N | Z44: 673
A45: 614 | B45: 202102 | C45: 印度 | D45: VOML机场数据 | E45: SUP 29/21 | F45: 4 | G45: 20210218e55694cf-3ef2-40c9-ab3d-60182e9fac80.txt | J45: 2021-02-11 00:00 | K45: 2999-12-31 00:00 | M45: 215443 | N45: 张荷竞 | O45: 袁伟英 | P45: 2021-02-18 10:24 | Q45: /全球AIP/亚洲/印度/SUP | R45: Y | S45: 459722 | T45: 2021-02-20 16:45 | U45: N | Z45: 674
A46: 615 | B46: 202102 | C46: 印度 | D46: VOBL机场ATC监视最低高度表 | E46: SUP 30/21 | F46: 29 | G46: 2021021879ab9091-16af-4b49-933d-65d4d0c3e334.txt | J46: 2021-02-11 00:00 | K46: 2999-12-31 00:00 | M46: 215443 | N46: 张荷竞 | O46: 刘云鹏 | P46: 2021-02-18 10:26 | Q46: /全球AIP/亚洲/印度/SUP | R46: Y | S46: 459723 | T46: 2021-02-19 16:48 | U46: N | Z46: 675
A47: 616 | B47: 202102 | C47: 中国台湾 | D47: 机场图 | E47: 台湾AIP AMDT02/21(AD 2-RCTP-45) | F47: 4,29 | G47: 20210218e4dd237b-f927-4403-a668-5bb9f8f0d636.txt | H47: 1,12,17 | I47: 飞行总队,运指签派 | J47: 2021-03-11 00:00 | K47: 2999-12-31 00:00 | L47: 对地面运行有影响，请相关部门注意 | M47: 182358 | N47: 何萍 | O47: 袁伟英 | P47: 2021-02-18 10:26 | Q47: /全球AIP/亚洲/中国台湾/AMDT | R47: Y | T47: 2021-02-20 16:49 | U47: N | Z47: 676
A48: 617 | B48: 202102 | C48: 印度 | D48: VOBLRWY 09L/27R投入使用 | E48: SUP 31/21 | F48: 20 | G48: 2021021874a662a3-7ac8-423b-8614-636040a39182.txt | J48: 2021-03-25 00:00 | K48: 2999-12-31 00:00 | M48: 215443 | N48: 张荷竞 | O48: 袁伟英 | P48: 2021-02-18 10:29 | Q48: /全球AIP/亚洲/印度/SUP | R48: Y | S48: 459726 | T48: 2021-02-20 16:48 | U48: N | Z48: 677
A49: 618 | B49: 202102 | C49: 拉脱维亚 | D49: 撤销直升机机场EVOC | E49: SUP 3/21 | F49: 29 | G49: 20210218f2aa7582-eb63-4196-8b9c-8196d6e33dc4.txt | J49: 2021-02-18 00:00 | K49: 2021-03-19 23:59 | L49: 暂无影响。 | M49: 215474 | N49: 甄薇 | O49: 袁伟英 | P49: 2021-02-18 10:29 | Q49: /全球AIP/欧洲/拉脱维亚/SUP | R49: Y | S49: 459725 | T49: 2021-02-20 16:48 | U49: N | Z49: 678
A50: 619 | B50: 202102 | C50: 中国台湾 | D50: 机场图（灯光） | E50: 台湾AIP AMDT02/21(AD 2-RCTP-47) | F50: 4,29 | G50: 2021021866d04443-c862-42a0-b88f-b27a46ef3821.txt | H50: 1,12,17 | I50: 飞行总队,运指签派 | J50: 2021-03-11 00:00 | K50: 2999-12-31 00:00 | L50: 对地面运行有影响，请相关部门注意 | M50: 182358 | N50: 何萍 | O50: 袁伟英 | P50: 2021-02-18 10:30 | Q50: /全球AIP/亚洲/中国台湾/AMDT | R50: Y | T50: 2021-02-20 16:48 | U50: N | Z50: 679
A51: 620 | B51: 202102 | C51: 印度 | D51: VEJH机场名变更 | E51: SUP 32/21 | F51: 4 | G51: 202102182f2d30d2-9ed4-4d5c-9682-a4ece336eab2.txt | J51: 2021-03-25 00:00 | K51: 2999-12-31 00:00 | M51: 215443 | N51: 张荷竞 | O51: 袁伟英 | P51: 2021-02-18 10:31 | Q51: /全球AIP/亚洲/印度/SUP | R51: Y | S51: 459727 | T51: 2021-02-20 16:48 | U51: N | Z51: 680
A52: 621 | B52: 202102 | C52: 拉脱维亚 | D52: 撤销直升机机场EVJC | E52: SUP 4/21 | F52: 29 | G52: 202102187081f6b1-637a-4054-9036-df70a0c737fc.txt | J52: 2021-02-25 00:00 | K52: 2021-03-19 23:59 | L52: 暂无影响。 | M52: 215474 | N52: 甄薇 | O52: 袁伟英 | P52: 2021-02-18 10:32 | Q52: /全球AIP/欧洲/拉脱维亚/SUP | R52: Y | S52: 459728 | T52: 2021-02-20 16:48 | U52: N | Z52: 681
A53: 622 | B53: 202102 | C53: 印度 | D53: VOBM机场名变更 | E53: SUP 33/21 | F53: 4 | G53: 20210218d5b4fef7-5161-44ec-9bbb-e23123cff2cd.txt | J53: 2021-02-11 00:00 | K53: 2999-12-31 00:00 | L53: 无影响 | M53: 215443 | N53: 张荷竞 | O53: 袁伟英 | P53: 2021-02-18 10:33 | Q53: /全球AIP/亚洲/印度/SUP | R53: Y | S53: 459729 | T53: 2021-02-20 16:45 | U53: N | Z53: 682
A54: 624 | B54: 202102 | C54: 印度 | D54: VEPT仪表进近图 | E54: SUP 34/21 | F54: 31 | G54: 202102187f0eb61f-a5c3-40ef-b7f4-e0962e8c72e9.txt | J54: 2021-02-11 00:00 | K54: 2999-12-31 00:00 | L54: 无影响 | M54: 215443 | N54: 张荷竞 | O54: 袁伟英 | P54: 2021-02-18 10:35 | Q54: /全球AIP/亚洲/印度/SUP | R54: Y | S54: 459730 | T54: 2021-02-20 16:32 | U54: N | Z54: 684
A55: 627 | B55: 202102 | C55: 尼泊尔 | D55: 分别修订机场VNSK和VNTJ的信息 | E55: S01/21、 S02/21 | F55: 20 | G55: 2021021857bbec9f-9712-4659-9476-5f3b4e2e0e1f.txt | J55: 2021-02-10 00:00 | K55: 2999-12-31 00:00 | L55: 暂无影响 | M55: 207803 | N55: 袁伟英 | O55: 袁伟英 | P55: 2021-02-18 13:57 | Q55: /全球AIP/亚洲/尼泊尔/SUP/2021 | R55: Y | S55: 459732,459733 | T55: 2021-02-19 09:16 | U55: N | Z55: 687
A56: 629 | B56: 202102 | C56: 伊朗 | D56: 伊朗航路信息修订 | E56: SUP 2、3、4、5、6、7、8/21 | F56: 15 | G56: 20210218d75dd24a-f327-4a25-bcf1-e2daa7363785.txt | J56: 2021-03-25 00:00 | K56: 2999-12-31 00:00 | L56: 暂无影响 | M56: 207803 | N56: 袁伟英 | O56: 袁伟英 | P56: 2021-02-18 14:22 | Q56: /全球AIP/亚洲/伊朗/SUP/2021 | R56: Y | S56: 459736,459737,459738,459739,459740,459741,459742 | T56: 2021-02-19 09:16 | U56: N | Z56: 689
A57: 630 | B57: 202102 | C57: 波兰 | D57: 激活跳伞活动区域 | E57: SUP 23/21 | F57: 16 | G57: 20210218e05ac874-ecea-4e9f-b54a-4790834d4ee8.txt | J57: 2021-04-12 00:00 | K57: 2021-06-18 23:59 | L57: 暂无影响。 | M57: 215474 | N57: 甄薇 | O57: 袁伟英 | P57: 2021-02-18 14:40 | Q57: /全球AIP/欧洲/波兰/SUP | R57: Y | S57: 459747 | T57: 2021-02-20 16:28 | U57: N | Z57: 690
A58: 631 | B58: 202102 | C58: 中国台湾 | D58: 撤除西港Sigang DME(NNN) | E58: 台湾AIP AMDT02/21(GEN2.5-2) | F58: 10 | G58: 2021022752cbac31-1857-4171-a31b-261a6243e110.txt | J58: 2021-03-25 00:00 | K58: 2999-12-31 00:00 | L58: 暂无影响 | M58: 182358 | N58: 何萍 | O58: 袁伟英 | P58: 2021-02-18 14:45 | Q58: /全球AIP/亚洲/中国台湾/AMDT | R58: Y | S58: 459749 | T58: 2021-02-27 11:06 | U58: N | Z58: 691
A59: 633 | B59: 202102 | C59: 波兰 | D59: 激活军事训练区域 | E59: SUP 24/21 | F59: 16 | G59: 20210218ddb35a3b-8c4d-4633-9c3f-8de2a836c4d3.txt | J59: 2021-03-25 00:00 | K59: 2021-10-29 23:59 | L59: 暂无影响。 | M59: 215474 | N59: 甄薇 | O59: 袁伟英 | P59: 2021-02-18 14:53 | Q59: /全球AIP/欧洲/波兰/SUP | R59: Y | S59: 459750 | T59: 2021-02-20 16:28 | U59: N | Z59: 693
A60: 635 | B60: 202102 | C60: 波兰 | D60: EPWA机场附近临时新增障碍物 | E60: SUP 25/21 | F60: 24 | G60: 202102187cf3e301-52d5-41e2-bb5a-6000571006d4.txt | J60: 2021-03-25 00:00 | K60: 2999-12-31 00:00 | L60: 非正班航点，暂无影响。 | M60: 215474 | N60: 甄薇 | O60: 袁伟英 | P60: 2021-02-18 15:00 | Q60: /全球AIP/欧洲/波兰/SUP | R60: Y | S60: 459751 | T60: 2021-02-20 16:28 | U60: N | Z60: 695
A61: 636 | B61: 202102 | C61: 波兰 | D61: EPWA机场附近新增障碍物 | E61: SUP 26/21 | F61: 24 | G61: 20210218920f88aa-79c6-4861-ad11-5a1e24fc3e89.txt | J61: 2021-03-25 00:00 | K61: 2999-12-31 00:00 | L61: 非正班航点，暂无影响。 | M61: 215474 | N61: 甄薇 | O61: 袁伟英 | P61: 2021-02-18 15:02 | Q61: /全球AIP/欧洲/波兰/SUP | R61: Y | S61: 459753 | T61: 2021-02-20 16:28 | U61: N | Z61: 696
A62: 637 | B62: 202102 | C62: 马尔代夫 | D62: Dhaalu飞行信息区空中运动区域 | E62: SUP 14/21 | F62: 16 | G62: 20210218f3a03905-a953-4cad-853a-e8cd7e85da71.txt | J62: 2021-03-01 00:00 | K62: 2999-12-31 00:00 | L62: 无影响 | M62: 215443 | N62: 张荷竞 | O62: 刘云鹏 | P62: 2021-02-18 15:04 | Q62: /全球AIP/亚洲/马尔代夫/SUP | R62: Y | S62: 459754 | T62: 2021-02-19 15:41 | U62: N | Z62: 697
A63: 639 | B63: 202102 | C63: 法国 | D63: 法国因军演建立临时限制区 | E63: SUP 025/21 | F63: 16 | G63: 20210218c2ea54b0-5cc7-463b-80b6-79387a03965e.txt | J63: 2021-03-10 00:00 | K63: 2021-03-12 00:00 | L63: 暂无影响 | M63: 207803 | N63: 袁伟英 | O63: 袁伟英 | P63: 2021-02-18 15:22 | Q63: /全球AIP/欧洲/法国/SUP | R63: Y | S63: 459752 | T63: 2021-02-19 09:15 | U63: N | Z63: 699
... A66: 643 | B66: 202102 | C66: 法国 | D66: LFOB机场新增RNAV SID初始离场程序 | E66: SUP 28/21 | F66: 31 | G66: 20210218947e6076-c4c0-4579-80a6-5865592db06c.txt | J66: 2021-03-25 00:00 | K66: 2021-09-08 00:00 | L66: 暂无影响 | M66: 207803 | N66: 袁伟英 | O66: 袁伟英 | P66: 2021-02-18 15:35 | Q66: /全球AIP/欧洲/法国/SUP | R66: Y | S66: 459759 | T66: 2021-02-19 09:14 | U66: N | Z66: 703
A67: 648 | B67: 202102 | C67: 日本 | D67: 日本筑城机场跑道开放时间调整 | E67: RJ SUP 011/21 | F67: 4 | G67: 2021021881810406-1920-4fc2-be3a-6a7a68738e0d.txt | J67: 2021-03-25 00:00 | K67: 2999-12-31 00:00 | L67: 非EFB列表机场，南航不使用，暂无影响。 | M67: 215456 | N67: 刘云鹏 | O67: 刘云鹏 | P67: 2021-02-18 18:49 | Q67: /全球AIP/亚洲/日本/SUP/2021 | R67: Y | T67: 2021-02-18 19:52 | U67: N | Z67: 708
A68: 649 | B68: 202102 | C68: 日本 | D68: 日本山形机场修订仪表进近程序 | E68: RJ SUP 012/21 | F68: 32 | G68: 20210218f6b6d499-c411-4d74-9a2f-163dba5877cb.txt | J68: 2021-03-25 00:00 | K68: 2999-12-31 00:00 | L68: 具体情况请以Jeppesen航图为准。 | M68: 215456 | N68: 刘云鹏 | O68: 刘云鹏 | P68: 2021-02-18 18:57 | Q68: /全球AIP/亚洲/日本/SUP/2021 | R68: Y | S68: 460815 | T68: 2021-02-18 19:52 | U68: N | Z68: 709
A69: 650 | B69: 202102 | C69: 日本 | D69: 日本针对小型航空器实施RNAV航路试验 | E69: RJ SUP 013/21 | F69: 2 | G69: 20210218eb5e3350-591b-4069-89b8-410d9195d161.txt | J69: 2021-03-25 00:00 | K69: 2999-12-31 00:00 | L69: 对运行无影响。 | M69: 215456 | N69: 刘云鹏 | O69: 刘云鹏 | P69: 2021-02-18 19:02 | Q69: /全球AIP/亚洲/日本/SUP/2021 | R69: Y | T69: 2021-02-18 19:52 | U69: N | Z69: 710
A70: 652 | B70: 202102 | C70: 日本 | D70: 函馆机场新增一张目视参考图 | E70: RJ NR2 AMDT RJCH AD2.24 | F70: 5 | G70: 20210218be479bbb-ef76-4ed3-9ce0-a52aa00b0981.txt | H70: 12 | J70: 2021-02-25 00:00 | K70: 2999-12-31 00:00 | L70: 非南航航点，暂无影响。 | M70: 215456 | N70: 刘云鹏 | O70: 刘云鹏 | P70: 2021-02-18 19:26 | Q70: /全球AIP/亚洲/日本/AMDT/2021/2.25 | R70: Y | S70: 460817 | T70: 2021-02-18 19:52 | U70: N | Z70: 712
A71: 654 | B71: 202102 | C71: 日本 | D71: 日本仙台机场继续实施多天线接收系统试验 | E71: RJ AIC 005/21 | F71: 26 | G71: 20210218647278b6-42b2-4498-b53f-3e3e2047752e.txt | H71: 1,8,12,17 | I71: 飞行总队,法标部,运指签派 | J71: 2021-02-25 00:00 | K71: 2025-03-31 19:46 | L71: 请运行人员关注。 | M71: 215456 | N71: 刘云鹏 | O71: 刘云鹏 | P71: 2021-02-18 19:47 | Q71: /全球AIP/亚洲/日本/AIC/2021 | R71: Y | S71: 460818 | T71: 2021-02-18 19:52 | U71: N | Z71: 714
A72: 655 | B72: 202102 | C72: 日本 | D72: 日本鹿儿岛机场实施CDO运行 | E72: RJ AIC 006/21 RJFK | F72: 31,32 | G72: 202102180f2e5918-d706-43ad-bd91-7b2d85b89270.txt | H72: 1,8,12,17 | I72: 飞行总队,法标部,运指签派 | J72: 2021-03-25 00:00 | K72: 2021-12-31 00:00 | L72: 请运行人员了解。 | M72: 215456 | N72: 刘云鹏 | O72: 刘云鹏 | P72: 2021-02-18 19:51 | Q72: /全球AIP/亚洲/日本/AIC/2021 | R72: Y | S72: 460819 | T72: 2021-02-18 19:52 | U72: N | Z72: 715
A73: 656 | B73: 202102 | C73: 芬兰 | D73: 修订对于国家航空器的规定 | E73: SUP 08/21 | F73: 7 | G73: 20210219f0f8ddba-c27e-418c-b2d8-4b517d1c2aae.txt | H73: 1,5,8,12,15,17 | I73: 飞行总队,机务工程部,法标部,运指航务,运指签派 | J73: 2021-02-18 00:00 | K73: 2999-12-31 00:00 | M73: 207803 | N73: 袁伟英 | O73: 袁伟英 | P73: 2021-02-19 09:24 | Q73: /全球AIP/欧洲/芬兰/SUP | R73: Y | S73: 461729 | T73: 2021-02-19 09:29 | U73: N | Z73: 716
A74: 657 | B74: 202102 | C74: 芬兰 | D74: 芬兰情报区建立临时危险区 | E74: SUP 09、10、11、12/2021 | F74: 16 | G74: 2021021956c91ee0-aee2-4a5a-916c-61da4c043c23.txt | J74: 2021-03-06 00:00 | K74: 2999-12-31 00:00 | L74: 暂无影响 | M74: 207803 | N74: 袁伟英 | O74: 袁伟英 | P74: 2021-02-19 09:29 | Q74: /全球AIP/欧洲/芬兰/SUP | R74: Y | S74: 461730,461731,461732,461733 | T74: 2021-02-19 09:29 | U74: N | Z74: 717
A75: 663 | B75: 202102 | C75: 德国 | D75: 修订ENR1.5-17内容 | E75: AMDT 02/21 ENR1.5-17 | F75: 15 | G75: 202102194a3d6498-f94e-4fbd-8ba7-4d034a7b6cee.txt | H75: 1,8,12,17 | I75: 飞行总队,法标部,运指签派 | J75: 2021-02-25 00:00 | K75: 2999-12-31 00:00 | L75: 请相关单位关注 | M75: 207803 | N75: 袁伟英 | O75: 刘云鹏 | P75: 2021-02-19 13:18 | Q75: /全球AIP/欧洲/德国/AMDT | R75: Y | T75: 2021-02-19 14:36 | U75: N | Z75: 723
A76: 673 | B76: 202102 | C76: 芬兰 | D76: 芬兰公布截至2022年4月21日的AIRAC生效日期 | E76: AIC 01/21 | F76: 6 | G76: 20210219211fd3fb-18e4-4d6f-ae9b-1fac1312cd83.txt | J76: 2021-02-18 00:00 | K76: 2999-12-31 00:00 | L76: 暂无影响 | M76: 207803 | N76: 袁伟英 | O76: 刘云鹏 | P76: 2021-02-19 15:12 | Q76: /全球AIP/欧洲/芬兰/AIC | R76: Y | S76: 461746 | T76: 2021-02-19 15:46 | U76: N | Z76: 733
A77: 674 | B77: 202102 | C77: 丹麦 | D77: 外部无线电话控制器的批准程序 | E77: AIC B 5/21 | F77: 10 | G77: 20210219ffa61e70-4336-49bd-b967-981df2b6eb3a.txt | J77: 2021-02-17 00:00 | K77: 2999-12-31 00:00 | L77: 暂无影响。 | M77: 215474 | N77: 甄薇 | O77: 刘云鹏 | P77: 2021-02-19 15:19 | Q77: /全球AIP/欧洲/丹麦/AIC/B | R77: Y | S77: 461747 | T77: 2021-02-19 15:46 | U77: N | Z77: 734
A78: 676 | B78: 202102 | C78: 澳大利亚 | D78: YOLD机场修订ERSA机场信息和RDS跑道长度 | E78: SUP H30/21 | F78: 4 | G78: 202102198e0f06bc-bb98-4e97-8140-eff0747006f1.txt | H78: 12 | J78: 2021-02-28 00:00 | K78: 2021-03-25 15:57 | L78: 暂无影响 | M78: 202984 | N78: 刘洋 | O78: 刘云鹏 | P78: 2021-02-19 15:52 | Q78: /全球AIP/大洋洲/澳大利亚/SUP/2021 | R78: Y | S78: 461749 | T78: 2021-02-19 16:31 | U78: N | Z78: 736
A79: 678 | B79: 202102 | C79: 澳大利亚 | D79: YPDN机场更新RWY 29 RNAV进近程序 | E79: AIRAC SUP H31/21 | F79: 5,32 | G79: 20210219ff210f2e-59f4-4b81-a38b-0da94eb8fa2c.txt | H79: 1,12,14,17 | I79: 飞行总队,运指性能,运指签派 | J79: 2021-04-21 16:00 | K79: 2021-06-17 16:11 | L79: YPDN RWY 29RNAV程序修订，跟踪JEPPESEN航图修订 | M79: 202984 | N79: 刘洋 | O79: 刘云鹏 | P79: 2021-02-19 16:06 | Q79: /全球AIP/大洋洲/澳大利亚/SUP/2021 | R79: Y | S79: 461750 | T79: 2021-02-19 16:28 | U79: N | Z79: 738
A80: 680 | B80: 202102 | C80: 加拿大 | D80: CYQF机场建立新的应答机区域 | E80: SUP 06/21 | F80: 29 | G80: 2021022001e8c039-e7b9-4af0-8cfa-e94cc187b35a.txt | J80: 2021-02-25 00:00 | K80: 2999-12-31 00:00 | L80: 暂无影响 | M80: 207803 | N80: 袁伟英 | O80: 袁伟英 | P80: 2021-02-20 09:47 | Q80: /全球AIP/中北美及加勒比/加拿大/SUP/2021 | R80: Y | S80: 461760 | T80: 2021-02-20 16:27 | U80: N | Z80: 740
A81: 681 | B81: 202102 | C81: 加拿大 | D81: CHG2机场新增起重机障碍物 | E81: SUP 07/21 | F81: 24 | G81: 20210220d19ebd6b-b9b2-48b6-ae9a-40d9b728f58f.txt | J81: 2021-02-25 00:00 | K81: 2999-12-31 00:00 | L81: 暂无影响 | M81: 207803 | N81: 袁伟英 | O81: 袁伟英 | P81: 2021-02-20 09:50 | Q81: /全球AIP/中北美及加勒比/加拿大/SUP/2021 | R81: Y | S81: 461762 | T81: 2021-02-20 16:27 | U81: N | Z81: 741
A82: 685 | B82: 202102 | C82: 加拿大 | D82: THUNDER BAY新建F级警戒空域 | E82: AIC 04/21 | F82: 16 | G82: 20210220306a8670-81cd-4193-8cc5-86fcf64f5e12.txt | J82: 2021-04-22 09:01 | K82: 2999-12-31 00:00 | L82: 暂无影响 | M82: 207803 | N82: 袁伟英 | O82: 袁伟英 | P82: 2021-02-20 10:17 | Q82: /全球AIP/中北美及加勒比/加拿大/AIC/2021 | R82: Y | S82: 461765 | T82: 2021-02-20 16:26 | U82: N | Z82: 745
A83: 689 | B83: 202102 | C83: 加拿大 | D83: 加拿大交通部发布公告说明飞越冲突地区 | E83: AIC 07/21 | F83: 9 | G83: 202102207f1188da-6c80-427f-b3fd-8f6962697bb9.txt | J83: 2021-02-25 00:00 | K83: 2999-12-31 00:00 | L83: 属加拿大官方定义的冲突地区说明，暂无影响 | M83: 207803 | N83: 袁伟英 | O83: 袁伟英 | P83: 2021-02-20 10:56 | Q83: /全球AIP/中北美及加勒比/加拿大/AIC/2021 | R83: Y | S83: 461770 | T83: 2021-02-20 16:26 | U83: N | Z83: 749
A84: 697 | B84: 202102 | C84: 波兰 | D84: EPGD机场低能见度程序运行 | E84: SUP 31/21 | F84: 28 | G84: 202102228dbb1505-aab0-46e0-bc23-5c7fe0605789.txt | J84: 2021-03-25 00:00 | K84: 2999-12-31 00:00 | L84: 非正班运行航点，暂无影响。 | M84: 215474 | N84: 甄薇 | O84: 袁伟英 | P84: 2021-02-22 14:40 | Q84: /全球AIP/欧洲/波兰/SUP | R84: Y | S84: 461778 | T84: 2021-02-22 17:44 | U84: N | Z84: 757
A85: 698 | B85: 202102 | C85: 波兰 | D85: EPGD机场施工 | E85: SUP 32/21 | F85: 23 | G85: 202102224d3c72f5-b7c4-4bdf-9aa2-d523b5f0d3d0.txt | J85: 2021-03-25 00:00 | K85: 2999-12-31 00:00 | L85: 非正班运行航点，暂无影响。 | M85: 215474 | N85: 甄薇 | O85: 袁伟英 | P85: 2021-02-22 14:44 | Q85: /全球AIP/欧洲/波兰/SUP | R85: Y | S85: 461779 | T85: 2021-02-22 17:44 | U85: N | Z85: 758
A86: 701 | B86: 202102 | C86: 奥地利 | D86: 公布奥地利2021至2022年定期及非定期的AIP生效时间 | E86: AIC 04/21 | F86: 6 | G86: 20210222d72f27cb-4f8c-43a8-8e66-67b22cf9fbc1.txt | H86: 12 | J86: 2021-02-25 00:00 | K86: 2999-12-31 00:00 | L86: 简单了解 | M86: 207803 | N86: 袁伟英 | O86: 袁伟英 | P86: 2021-02-22 17:31 | Q86: /全球AIP/欧洲/奥地利/AIC | R86: Y | S86: 461783 | T86: 2021-02-22 17:43 | U86: N | Z86: 761
A87: 702 | B87: 202102 | C87: 奥地利 | D87: 修订奥地利新比例的航图订购方式 | E87: AIC 05/21 | F87: 6 | G87: 20210222e2ac5d87-2147-43c6-b4c1-2a58166fe3bf.txt | J87: 2021-02-25 00:00 | K87: 2999-12-31 00:00 | L87: 暂无影响 | M87: 207803 | N87: 袁伟英 | O87: 袁伟英 | P87: 2021-02-22 17:37 | Q87: /全球AIP/欧洲/奥地利/AIC | R87: Y | S87: 461784 | T87: 2021-02-22 17:43 | U87: N | Z87: 762
A88: 703 | B88: 202102 | C88: 奥地利 | D88: 旋翼机进出LOGH直升机场的IFR程序 | E88: AIC 06/21 | F88: 32 | G88: 2021022221e38777-705b-4f89-8298-da3bb7eb6f20.txt | J88: 2021-03-25 00:00 | K88: 2999-12-31 00:00 | L88: 暂无影响 | M88: 207803 | N88: 袁伟英 | O88: 袁伟英 | P88: 2021-02-22 17:42 | Q88: /全球AIP/欧洲/奥地利/AIC | R88: Y | S88: 461785 | T88: 2021-02-22 17:43 | U88: N | Z88: 763
A89: 704 | B89: 202102 | C89: 中国台湾 | D89: 桃园国际棒球场烟火施放 | E89: 台湾AIP SUP04/2 | F89: 6 | G89: 20210223dc5f8c48-14ab-405d-bddb-6763aed96bd6.txt | H89: 1,12,17 | I89: 飞行总队,运指签派 | J89: 2021-04-03 11:00 | K89: 2021-11-14 14:00 | L89: 对运行有影响，请相关部门注意 | M89: 182358 | N89: 何萍 | O89: 袁伟英 | P89: 2021-02-23 16:47 | Q89: /全球AIP/亚洲/中国台湾/SUP/2021 | R89: Y | S89: 461787 | T89: 2021-02-27 12:20 | U89: N | Z89: 764
A90: 705 | B90: 202102 | C90: 澳大利亚 | D90: TEMORA空军百年纪念表演21年3月6日至7日 | E90: SUP H32/21 | F90: 16 | G90: 20210224c2fccd20-3f0b-4f34-af41-fa96635c77ab.txt | H90: 12,17 | I90: 运指签派 | J90: 2021-03-06 00:00 | K90: 2021-03-07 10:49 | L90: 暂不影响公司航线，请导航位评估运行影响 | M90: 202984 | N90: 刘洋 | O90: 刘云鹏 | P90: 2021-02-24 10:49 | Q90: /全球AIP/大洋洲/澳大利亚/SUP/2021 | R90: Y | S90: 461788 | T90: 2021-02-25 18:22 | U90: N | Z90: 765
A91: 706 | B91: 202102 | C91: 澳大利亚 | D91: 3月25日生效周期修订澳洲DAH和ERSA手册 | E91: AIRAC SUP H33/21 | F91: 12 | G91: 20210224f060b0dd-623e-401a-9d90-b091146a90d7.txt | H91: 12 | J91: 2021-03-25 00:00 | K91: 2999-12-31 00:00 | L91: 删除航路点对公司航线无影响， 新增航路点涉及基础数据修订，请导航室评估运行影响 | M91: 202984 | N91: 刘洋 | O91: 刘云鹏 | P91: 2021-02-24 11:24 | Q91: /全球AIP/大洋洲/澳大利亚/SUP/2021 | R91: Y | S91: 461789 | T91: 2021-02-25 16:31 | U91: N | Z91: 766
A92: 707 | B92: 202102 | C92: 澳大利亚 | D92: YOLD机场修订进近程序 | E92: SUP H28/21 | F92: 5,32 | G92: 202102242c7ac9e8-dc02-4580-8299-e4d41b7d9b07.txt | H92: 12 | J92: 2021-02-28 00:00 | K92: 2999-12-31 00:00 | L92: 暂无影响 | M92: 202984 | N92: 刘洋 | O92: 刘云鹏 | P92: 2021-02-24 13:08 | Q92: /全球AIP/大洋洲/澳大利亚/SUP/2021 | R92: Y | S92: 461790 | T92: 2021-02-25 18:23 | U92: N | Z92: 767
A93: 708 | B93: 202102 | C93: 澳大利亚 | D93: YSTW机场替换地面灯光 | E93: AIC H05/21 | F93: 21,27 | G93: 20210224e77b2eef-f8de-4781-a5e7-22595e37b1a0.txt | H93: 12 | J93: 2021-02-28 00:00 | K93: 2999-12-31 00:00 | L93: 暂无影响 | M93: 202984 | N93: 刘洋 | O93: 刘云鹏 | P93: 2021-02-24 14:10 | Q93: /全球AIP/大洋洲/澳大利亚/AIC/2021 | R93: Y | S93: 458546 | T93: 2021-02-25 18:23 | U93: N | Z93: 768
A94: 713 | B94: 202102 | C94: 中国香港 | D94: 飞机停放图 | E94: 香港AIP AMDT(AD 2-VHHH-ADC-4) | F94: 4,29 | G94: 2021022570e23499-d0e3-4591-85ec-83515e05e4ff.txt | H94: 1,12,17 | I94: 飞行总队,运指签派 | J94: 2021-03-25 00:00 | K94: 2999-12-31 00:00 | L94: 对运行有影响，请相关部门注意 | M94: 182358 | N94: 何萍 | O94: 袁伟英 | P94: 2021-02-25 09:52 | Q94: /全球AIP/亚洲/中国香港/AMDT | R94: Y | T94: 2021-03-17 14:47 | U94: N | Z94: 773
A95: 716 | B95: 202102 | C95: 印度 | D95: VEDH机场仪表进近图 | E95: SUP 35/21 | F95: 31 | G95: 202102259ec7ab9e-4ccb-411b-a84a-89af01b9029b.txt | J95: 2021-04-22 00:00 | K95: 2999-12-31 00:00 | L95: 无影响 | M95: 215443 | N95: 张荷竞 | O95: 袁伟英 | P95: 2021-02-25 13:46 | Q95: /全球AIP/亚洲/印度/SUP | R95: Y | S95: 461792 | T95: 2021-02-26 13:22 | U95: N | Z95: 776
A96: 717 | B96: 202102 | C96: 印度 | D96: VEDH机场仪表进近图 | E96: SUP 36/21 | F96: 31 | G96: 20210225c77f1722-3eb2-4584-a7c3-780558b5fe07.txt | J96: 2021-04-22 00:00 | K96: 2999-12-31 00:00 | L96: 无影响 | M96: 215443 | N96: 张荷竞 | O96: 袁伟英 | P96: 2021-02-25 13:47 | Q96: /全球AIP/亚洲/印度/SUP | R96: Y | S96: 461793 | T96: 2021-02-26 13:22 | U96: N | Z96: 777
A97: 728 | B97: 202102 | C97: 瑞典 | D97: 激活限制区R05的延伸区域 | E97: SUP 22/21 | F97: 19 | G97: 202102265612956e-ce8b-474a-8764-7bd20646f1cf.txt | J97: 2021-03-17 00:00 | K97: 2021-03-24 00:00 | L97: 暂无影响。 | M97: 215474 | N97: 甄薇 | O97: 袁伟英 | P97: 2021-02-26 08:51 | Q97: /全球AIP/欧洲/瑞典/SUP | R97: Y | S97: 461800 | T97: 2021-02-26 13:15 | U97: N | Z97: 788
A98: 729 | B98: 202102 | C98: 瑞典 | D98: 激活临时限制区域HAGELBERG North | E98: SUP 23/21 | F98: 19 | G98: 202102262e756162-e540-40eb-987e-f5831d1a907e.txt | J98: 2021-03-23 00:00 | K98: 2021-03-24 00:00 | L98: 暂无影响。 | M98: 215474 | N98: 甄薇 | O98: 袁伟英 | P98: 2021-02-26 08:57 | Q98: /全球AIP/欧洲/瑞典/SUP | R98: Y | S98: 461801 | T98: 2021-02-26 13:14 | U98: N | Z98: 789
A99: 730 | B99: 202103 | C99: 瑞典 | D99: 各机场附近临时障碍物 | E99: SUP 24/21 | F99: 24 | G99: 2021022661cddb83-c8cb-45cb-8eef-979f9c733545.txt | J99: 2021-02-25 00:00 | K99: 2999-12-31 00:00 | L99: 非正班航点，暂无影响。 | M99: 215474 | N99: 甄薇 | O99: 袁伟英 | P99: 2021-02-26 09:03 | Q99: /全球AIP/欧洲/瑞典/SUP | R99: Y | S99: 527337 | T99: 2021-02-26 13:14 | U99: N | Z99: 790
A100: 731 | B100: 202103 | C100: 拉脱维亚 | D100: EVJA机场关闭国际运行及夜航运行 | E100: SUP 5/21 | F100: 29 | G100: 20210226c3c83101-040a-4523-8c64-4cd52aae6f6f.txt | J100: 2021-03-01 00:00 | K100: 2021-06-01 00:00 | L100: 非正班航点，暂无影响。 | M100: 215474 | N100: 甄薇 | O100: 袁伟英 | P100: 2021-02-26 09:19 | Q100: /全球AIP/欧洲/拉脱维亚/SUP | R100: Y | S100: 527338 | T100: 2021-02-26 13:14 | U100: N | Z100: 791
A101: 732 | B101: 202103 | C101: 芬兰 | D101: 修订基础机场EFOU进近程序的MSA | E101: SUP 13/21 | F101: 32 | G101: 20210226effccc9a-b1e3-4048-946f-fc485e903172.txt | J101: 2021-04-22 00:00 | K101: 2999-12-31 00:00 | L101: 暂无影响 | M101: 207803 | N101: 袁伟英 | O101: 袁伟英 | P101: 2021-02-26 12:53 | Q101: /全球AIP/欧洲/芬兰/SUP | R101: Y | S101: 527339 | T101: 2021-02-26 13:14 | U101: N | Z101: 792
A102: 733 | B102: 202103 | C102: 法国 | D102: 建立临时限制区 | E102: SUP 29/21 | F102: 16 | G102: 20210226b788d00a-cc7a-4c05-a3c1-bd4ab62b0123.txt | J102: 2021-03-16 00:00 | K102: 2021-03-24 00:00 | L102: 暂无影响 | M102: 207803 | N102: 袁伟英 | O102: 袁伟英 | P102: 2021-02-26 12:56 | Q102: /全球AIP/欧洲/法国/SUP | R102: Y | S102: 527340 | T102: 2021-02-26 13:14 | U102: N | Z102: 793
...

Sheet 三星以上
A1: countryName | B1: staffName | D1: 计数项:countryName
A2: 土耳其 | B2: 刘洋 | D2: staffName | E2: 汇总
A3: 印度 | B3: 张荷竞 | D3: 何萍 | E3: 24
A4: 中国香港 | B4: 何萍 | D4: 刘洋 | E4: 53
A5: 中国香港 | B5: 何萍 | D5: 刘云鹏 | E5: 25
A6: 中国香港 | B6: 张宁 | D6: 欧阳嘉兰 | E6: 2
A7: 越南 | B7: 张宁 | D7: 王钰婷 | E7: 21
A8: 马来西亚 | B8: 张荷竞 | D8: 王志铿 | E8: 1
A9: 英国 | B9: 袁伟英 | D9: 吴坤林 | E9: 14
A10: 俄罗斯 | B10: 刘洋 | D10: 吴奕铭 | E10: 32
A11: 英国 | B11: 袁伟英 | D11: 袁伟英 | E11: 61
A12: 荷兰 | B12: 袁伟英 | D12: 张荷竞 | E12: 14
A13: 拉脱维亚 | B13: 甄薇 | D13: 张宁 | E13: 16
A14: 阿联酋 | B14: 吴奕铭 | D14: 甄薇 | E14: 11
A15: 俄罗斯 | B15: 刘洋 | D15: 总计 | E15: 274
A16: 阿联酋 | B16: 吴奕铭
A17: 德国 | B17: 袁伟英
A18: 格鲁吉亚 | B18: 刘洋
A19: 格鲁吉亚 | B19: 刘洋
A20: 土耳其 | B20: 刘洋
A21: 土耳其 | B21: 刘洋
A22: 马尔代夫 | B22: 张荷竞
A23: 马尔代夫 | B23: 张荷竞
A24: 澳大利亚 | B24: 刘洋
A25: 格鲁吉亚 | B25: 刘洋
A26: 格鲁吉亚 | B26: 刘洋
A27: 中国香港 | B27: 何萍
... A275: 柬埔寨 | B275: 刘云鹏

Sheet 张宁
A1: countryName | B1: staffName
A2: 法国 | B2: 张宁
A3: 法国 | B3: 张宁
A4: 巴基斯坦 | B4: 张宁
A5: 巴基斯坦 | B5: 张宁
A6: 尼泊尔 | B6: 张宁
A7: 巴基斯坦 | B7: 张宁
A8: 马来西亚 | B8: 张宁
A9: 肯尼亚 | B9: 张宁
A10: 肯尼亚 | B10: 张宁
A11: 巴基斯坦 | B11: 张宁
A12: 巴基斯坦 | B12: 张宁
... A95: 孟加拉 | B95: 张宁

Sheet 甄薇
A1: countryName | B1: staffName
A2: 拉脱维亚 | B2: 甄薇
A3: 拉脱维亚 | B3: 甄薇
A4: 拉脱维亚 | B4: 甄薇
A5: 波兰 | B5: 甄薇
A6: 波兰 | B6: 甄薇
A7: 波兰 | B7: 甄薇
A8: 波兰 | B8: 甄薇
A9: 丹麦 | B9: 甄薇
A10: 波兰 | B10: 甄薇
A11: 波兰 | B11: 甄薇
A12: 瑞典 | B12: 甄薇
... A189: 白俄罗斯 | B189: 甄薇

Sheet 张荷竞
A1: countryName | B1: staffName
A2: 印度 | B2: 张荷竞
A3: 印度 | B3: 张荷竞
A4: 印度 | B4: 张荷竞
A5: 印度 | B5: 张荷竞
A6: 印度 | B6: 张荷竞
A7: 印度 | B7: 张荷竞
A8: 印度 | B8: 张荷竞
A9: 印度 | B9: 张荷竞
A10: 印度 | B10: 张荷竞
A11: 印度 | B11: 张荷竞
A12: 印度 | B12: 张荷竞
... A127: 马尔代夫 | B127: 张荷竞
B128: 张荷竞
B129: 张荷竞
B130: 张荷竞
B131: 张荷竞
B132: 张荷竞
B133: 张荷竞
B134: 张荷竞
A135: 巴基斯坦 | B135: 张荷竞
A136: 巴基斯坦 | B136: 张荷竞
A137: 巴基斯坦 | B137: 张荷竞
A138: 巴基斯坦 | B138: 张荷竞
A139: 印度 | B139: 张荷竞
A140: 马来西亚 | B140: 张荷竞
A141: 印度 | B141: 张荷竞
A142: 马来西亚 | B142: 张荷竞
A143: 马尔代夫 | B143: 张荷竞
A144: 马尔代夫 | B144: 张荷竞
A145: 马来西亚 | B145: 张荷竞
A146: 马来西亚 | B146: 张荷竞
... A177: 马来西亚 | B177: 张荷竞

Sheet 王康健
A1: countryName | B1: staffName
B2: 王康健
A3: 尼泊尔 | B3: 王康健

Sheet 王钰婷
A1: countryName | B1: staffName
A2: 比利时 | B2: 王钰婷
A3: 比利时 | B3: 王钰婷
A4: 比利时 | B4: 王钰婷
A5: 比利时 | B5: 王钰婷
A6: 比利时 | B6: 王钰婷
A7: 比利时 | B7: 王钰婷
A8: 比利时 | B8: 王钰婷
A9: 比利时 | B9: 王钰婷
A10: 比利时 | B10: 王钰婷
A11: 比利时 | B11: 王钰婷
A12: 比利时 | B12: 王钰婷
... A226: 泰国 | B226: 王钰婷

Sheet 吴坤林
A1: countryName | B1: staffName
A2: 越南 | B2: 吴坤林
A3: 越南 | B3: 吴坤林
A4: 印尼 | B4: 吴坤林
A5: 印尼 | B5: 吴坤林
A6: 印尼 | B6: 吴坤林
A7: 泰国 | B7: 吴坤林
A8: 泰国 | B8: 吴坤林
A9: 泰国 | B9: 吴坤林
A10: 泰国 | B10: 吴坤林
A11: 泰国 | B11: 吴坤林
A12: 泰国 | B12: 吴坤林
... A19: 印尼 | B19: 吴坤林
B20: 吴坤林
B21: 吴坤林
B22: 吴坤林
A23: 越南 | B23: 吴坤林
A24: 泰国 | B24: 吴坤林
A25: 越南 | B25: 吴坤林
A26: 泰国 | B26: 吴坤林
A27: 印尼 | B27: 吴坤林
A28: 印尼 | B28: 吴坤林
A29: 印尼 | B29: 吴坤林
A30: 印尼 | B30: 吴坤林
A31: 印尼 | B31: 吴坤林
A32: 印尼 | B32: 吴坤林
A33: 印尼 | B33: 吴坤林
A34: 印尼 | B34: 吴坤林
... A65: 越南 | B65: 吴坤林
B66: 吴坤林
B67: 吴坤林
B68: 吴坤林
B69: 吴坤林
B70: 吴坤林
B71: 吴坤林
B72: 吴坤林
B73: 吴坤林
B74: 吴坤林
B75: 吴坤林
B76: 吴坤林
B77: 吴坤林
... B92: 吴坤林
A93: 新加坡 | B93: 吴坤林
A94: 印尼 | B94: 吴坤林
A95: 印尼 | B95: 吴坤林
A96: 印尼 | B96: 吴坤林
A97: 印尼 | B97: 吴坤林
A98: 印尼 | B98: 吴坤林
A99: 印尼 | B99: 吴坤林
A100: 印尼 | B100: 吴坤林
A101: 印尼 | B101: 吴坤林
A102: 印尼 | B102: 吴坤林
A103: 新加坡 | B103: 吴坤林
A104: 越南 | B104: 吴坤林
... A176: 新加坡 | B176: 吴坤林

Sheet 吴奕铭
A1: countryName | B1: staffName
A2: 阿联酋 | B2: 吴奕铭
A3: 阿联酋 | B3: 吴奕铭
A4: 阿联酋 | B4: 吴奕铭
A5: 阿联酋 | B5: 吴奕铭
A6: 菲律宾 | B6: 吴奕铭
A7: 菲律宾 | B7: 吴奕铭
A8: 菲律宾 | B8: 吴奕铭
A9: 菲律宾 | B9: 吴奕铭
A10: 菲律宾 | B10: 吴奕铭
A11: 菲律宾 | B11: 吴奕铭
A12: 菲律宾 | B12: 吴奕铭
... A86: 阿联酋 | B86: 吴奕铭
B87: 吴奕铭
B88: 吴奕铭
B89: 吴奕铭
B90: 吴奕铭
B91: 吴奕铭
B92: 吴奕铭
B93: 吴奕铭
B94: 吴奕铭
B95: 吴奕铭
B96: 吴奕铭
B97: 吴奕铭
B98: 吴奕铭
... B113: 吴奕铭
A114: 韩国 | B114: 吴奕铭
A115: 韩国 | B115: 吴奕铭
A116: 韩国 | B116: 吴奕铭
A117: 韩国 | B117: 吴奕铭
A118: 韩国 | B118: 吴奕铭
A119: 韩国 | B119: 吴奕铭
A120: 韩国 | B120: 吴奕铭
A121: 韩国 | B121: 吴奕铭
A122: 韩国 | B122: 吴奕铭
A123: 韩国 | B123: 吴奕铭
A124: 韩国 | B124: 吴奕铭
A125: 韩国 | B125: 吴奕铭
... A303: 阿联酋 | B303: 吴奕铭

Sheet 杨子城
A1: countryName | B1: staffName
A2: 菲律宾 | B2: 杨子城
A3: 菲律宾 | B3: 杨子城
A4: 菲律宾 | B4: 杨子城
A5: 韩国 | B5: 杨子城
A6: 韩国 | B6: 杨子城
A7: 韩国 | B7: 杨子城
A8: 韩国 | B8: 杨子城
A9: 韩国 | B9: 杨子城
A10: 韩国 | B10: 杨子城
A11: 阿联酋 | B11: 杨子城
A12: 阿联酋 | B12: 杨子城
... A52: 韩国 | B52: 杨子城

Sheet 刘云鹏
A1: countryName | B1: staffName
A2: 日本 | B2: 刘云鹏
A3: 日本 | B3: 刘云鹏
A4: 日本 | B4: 刘云鹏
A5: 日本 | B5: 刘云鹏
A6: 日本 | B6: 刘云鹏
A7: 日本 | B7: 刘云鹏
A8: 日本 | B8: 刘云鹏
A9: 日本 | B9: 刘云鹏
A10: 日本 | B10: 刘云鹏 | G10: 柬埔寨 | H10: 老挝 | I10: 缅甸 | J10: 日本 | K10: 印度
A11: 日本 | B11: 刘云鹏 | G11: 3 | H11: 2 | I11: 2 | J11: 235 | K11: 18
A12: 日本 | B12: 刘云鹏
A13: 日本 | B13: 刘云鹏
A14: 日本 | B14: 刘云鹏
A15: 日本 | B15: 刘云鹏
A16: 日本 | B16: 刘云鹏
A17: 日本 | B17: 刘云鹏
A18: 日本 | B18: 刘云鹏
A19: 日本 | B19: 刘云鹏
A20: 日本 | B20: 刘云鹏
A21: 日本 | B21: 刘云鹏
A22: 日本 | B22: 刘云鹏
A23: 日本 | B23: 刘云鹏
... A142: 印度 | B142: 刘云鹏
B143: 刘云鹏
A144: 日本 | B144: 刘云鹏
B145: 刘云鹏
B146: 刘云鹏
B147: 刘云鹏
B148: 刘云鹏
B149: 刘云鹏
B150: 刘云鹏
B151: 刘云鹏
A152: 日本 | B152: 刘云鹏
A153: 日本 | B153: 刘云鹏
A154: 日本 | B154: 刘云鹏
A155: 日本 | B155: 刘云鹏
A156: 日本 | B156: 刘云鹏
A157: 日本 | B157: 刘云鹏
A158: 日本 | B158: 刘云鹏
A159: 日本 | B159: 刘云鹏
A160: 日本 | B160: 刘云鹏
A161: 日本 | B161: 刘云鹏
A162: 日本 | B162: 刘云鹏
A163: 日本 | B163: 刘云鹏
... A269: 日本 | B269: 刘云鹏

Sheet 刘洋
A1: countryName | B1: staffName
A2: 澳大利亚 | B2: 刘洋
A3: 澳大利亚 | B3: 刘洋
A4: 澳大利亚 | B4: 刘洋
A5: 澳大利亚 | B5: 刘洋
A6: 澳大利亚 | B6: 刘洋
A7: 澳大利亚 | B7: 刘洋
A8: 澳大利亚 | B8: 刘洋
A9: 澳大利亚 | B9: 刘洋
A10: 澳大利亚 | B10: 刘洋
A11: 澳大利亚 | B11: 刘洋
A12: 澳大利亚 | B12: 刘洋
... A139: 新西兰 | B139: 刘洋
B140: 刘洋
B141: 刘洋
B142: 刘洋
B143: 刘洋
B144: 刘洋
B145: 刘洋
B146: 刘洋
B147: 刘洋
B148: 刘洋
B149: 刘洋
B150: 刘洋
B151: 刘洋
... B167: 刘洋
A168: 俄罗斯 | B168: 刘洋
A169: 俄罗斯 | B169: 刘洋
A170: 俄罗斯 | B170: 刘洋
A171: 俄罗斯 | B171: 刘洋
A172: 俄罗斯 | B172: 刘洋
A173: 澳大利亚 | B173: 刘洋
A174: 澳大利亚 | B174: 刘洋
A175: 俄罗斯 | B175: 刘洋
A176: 澳大利亚 | B176: 刘洋
A177: 澳大利亚 | B177: 刘洋
A178: 俄罗斯 | B178: 刘洋
A179: 哈萨克斯坦 | B179: 刘洋
... A365: 俄罗斯 | B365: 刘洋

Sheet 袁伟英
A1: countryName | B1: staffName
A2: 法国 | B2: 袁伟英
A3: 法国 | B3: 袁伟英
A4: 意大利 | B4: 袁伟英
A5: 意大利 | B5: 袁伟英
A6: 法国 | B6: 袁伟英
A7: 法国 | B7: 袁伟英
A8: 英国 | B8: 袁伟英
A9: 英国 | B9: 袁伟英
A10: 英国 | B10: 袁伟英
A11: 英国 | B11: 袁伟英
A12: 英国 | B12: 袁伟英
... A357: 芬兰 | B357: 袁伟英
A358: 丹麦 | B358: 袁伟英 | L358: 爱沙尼亚 | M358: 奥地利 | N358: 波兰 | O358: 丹麦 | P358: 德国 | Q358: 法国 | R358: 芬兰 | S358: 荷兰 | T358: 加拿大 | U358: 拉脱维亚 | V358: 立陶宛 | W358: 瑞典 | X358: 意大利 | Y358: 英国
A359: 瑞典 | B359: 袁伟英 | L359: 12 | M359: 41 | N359: 20 | O359: 12 | P359: 61 | Q359: 231 | R359: 99 | S359: 37 | T359: 92 | U359: 13 | V359: 11 | W359: 40 | X359: 46 | Y359: 144
A360: 瑞典 | B360: 袁伟英
A361: 意大利 | B361: 袁伟英
A362: 丹麦 | B362: 袁伟英
A363: 英国 | B363: 袁伟英
A364: 英国 | B364: 袁伟英
A365: 英国 | B365: 袁伟英
A366: 英国 | B366: 袁伟英
A367: 英国 | B367: 袁伟英
A368: 英国 | B368: 袁伟英
A369: 英国 | B369: 袁伟英
A370: 法国 | B370: 袁伟英
A371: 法国 | B371: 袁伟英
... A587: 波兰 | B587: 袁伟英
B588: 袁伟英
B589: 袁伟英
B590: 袁伟英
B591: 袁伟英
B592: 袁伟英
B593: 袁伟英
B594: 袁伟英
B595: 袁伟英
B596: 袁伟英
B597: 袁伟英
B598: 袁伟英
B599: 袁伟英
... B610: 袁伟英
A611: 中国台湾 | B611: 袁伟英
A612: 意大利 | B612: 袁伟英
A613: 英国 | B613: 袁伟英
A614: 德国 | B614: 袁伟英
A615: 加拿大 | B615: 袁伟英
A616: 加拿大 | B616: 袁伟英
A617: 法国 | B617: 袁伟英
A618: 法国 | B618: 袁伟英
A619: 法国 | B619: 袁伟英
A620: 意大利 | B620: 袁伟英
A621: 英国 | B621: 袁伟英
A622: 韩国 | B622: 袁伟英
... A912: 波兰 | B912: 袁伟英

Sheet 欧阳嘉兰
A1: countryName | B1: staffName
A2: 印度 | B2: 欧阳嘉兰
A3: 日本 | B3: 欧阳嘉兰
A4: 日本 | B4: 欧阳嘉兰
A5: 日本 | B5: 欧阳嘉兰
A6: 日本 | B6: 欧阳嘉兰
A7: 日本 | B7: 欧阳嘉兰
A8: 日本 | B8: 欧阳嘉兰
A9: 日本 | B9: 欧阳嘉兰
A10: 日本 | B10: 欧阳嘉兰
A11: 日本 | B11: 欧阳嘉兰
A12: 印度 | B12: 欧阳嘉兰
... A109: 印度 | B109: 欧阳嘉兰

Sheet 何萍
A1: countryName | B1: staffName
A2: 中国台湾 | B2: 何萍
A3: 中国台湾 | B3: 何萍
A4: 中国台湾 | B4: 何萍
A5: 中国台湾 | B5: 何萍
A6: 中国台湾 | B6: 何萍
A7: 中国台湾 | B7: 何萍
A8: 中国香港 | B8: 何萍
A9: 中国香港 | B9: 何萍 | K9: 中国澳门 | L9: 中国台湾 | M9: 中国香港
A10: 中国香港 | B10: 何萍 | K10: 26 | L10: 62 | M10: 122
A11: 中国香港 | B11: 何萍
A12: 中国香港 | B12: 何萍
A13: 中国香港 | B13: 何萍
A14: 中国澳门 | B14: 何萍
A15: 中国台湾 | B15: 何萍
A16: 中国香港 | B16: 何萍
A17: 中国香港 | B17: 何萍
A18: 中国台湾 | B18: 何萍
A19: 中国香港 | B19: 何萍
A20: 中国香港 | B20: 何萍
A21: 中国香港 | B21: 何萍
A22: 中国澳门 | B22: 何萍
... A95: 中国台湾 | B95: 何萍
B96: 何萍
B97: 何萍
B98: 何萍
B99: 何萍
B100: 何萍
B101: 何萍
B102: 何萍
B103: 何萍
B104: 何萍
B105: 何萍
B106: 何萍
B107: 何萍
... B115: 何萍
A116: 中国澳门 | B116: 何萍
A117: 中国澳门 | B117: 何萍
A118: 中国澳门 | B118: 何萍
A119: 中国台湾 | B119: 何萍
A120: 中国台湾 | B120: 何萍
A121: 中国香港 | B121: 何萍
A122: 中国澳门 | B122: 何萍
A123: 中国香港 | B123: 何萍
A124: 中国台湾 | B124: 何萍
A125: 中国台湾 | B125: 何萍
A126: 中国香港 | B126: 何萍
A127: 中国香港 | B127: 何萍
... A231: 中国香港 | B231: 何萍

Sheet Sheet21
A1: 阿联酋 | B1: 爱沙尼亚 | C1: 奥地利 | D1: 澳大利亚 | E1: 巴基斯坦 | F1: 白俄罗斯 | G1: 比利时 | H1: 波兰 | I1: 丹麦 | J1: 德国 | K1: 俄罗斯 | L1: 法国 | M1: 菲律宾 | N1: 芬兰 | O1: 格鲁吉亚 | P1: 哈萨克斯坦 | Q1: 韩国 | R1: 荷兰 | S1: 加拿大 | T1: 柬埔寨 | U1: 肯尼亚 | V1: 拉脱维亚 | W1: 马尔代夫 | X1: 马来西亚 | Y1: 蒙古 | Z1: 孟加拉 | AA1: 尼泊尔 | AB1: 日本 | AC1: 瑞典 | AD1: 泰国 | AE1: 土耳其 | AF1: 乌兹别克斯坦 | AG1: 新加坡 | AH1: 新西兰 | AI1: 伊朗 | AJ1: 意大利 | AK1: 印度 | AL1: 印尼 | AM1: 英国 | AN1: 越南 | AO1: 中国台湾 | AP1: 中国香港
A2: 8 | B2: 1 | C2: 3 | D2: 25 | E2: 4 | F2: 1 | G2: 5 | H2: 7 | I2: 1 | J2: 8 | K2: 13 | L2: 9 | M2: 2 | N2: 3 | O2: 4 | P2: 3 | Q2: 20 | R2: 7 | S2: 11 | T2: 2 | U2: 1 | V2: 1 | W2: 3 | X2: 15 | Y2: 2 | Z2: 1 | AA2: 1 | AB2: 25 | AC2: 4 | AD2: 9 | AE2: 6 | AF2: 1 | AG2: 7 | AH2: 1 | AI2: 1 | AJ2: 4 | AK2: 2 | AL2: 6 | AM2: 11 | AN2: 9 | AO2: 1 | AP2: 25

Sheet Sheet22
A1: 中国香港 | B1: 25
A2: 日本 | B2: 25
A3: 澳大利亚 | B3: 25
A4: 韩国 | B4: 20
A5: 马来西亚 | B5: 15
A6: 俄罗斯 | B6: 13
A7: 英国 | B7: 11
A8: 加拿大 | B8: 11
A9: 越南 | B9: 9
A10: 泰国 | B10: 9
A11: 法国 | B11: 9
A12: 德国 | B12: 8
... A42: 爱沙尼亚 | B42: 1

Sheet Sheet19
A1: 国家 | B1: 记录数
A2: 日本 | B2: 326
A3: 法国 | B3: 236
A4: 韩国 | B4: 170
A5: 英国 | B5: 145
A6: 澳大利亚 | B6: 138
A7: 印度 | B7: 133
A8: 中国香港 | B8: 125
A9: 阿联酋 | B9: 121
A10: 瑞典 | B10: 105
A11: 芬兰 | B11: 101
A12: 泰国 | B12: 99
A13: 加拿大 | B13: 93
... A51: 孟加拉 | B51: 3

Sheet Sheet3
B1: 2021AIP数据总计.xls 兼容性报表
B2: 运行时间: 2022/1/25 14:06
B4: 如果工作簿以早期的文件格式保存或在早期版本的 Microsoft Excel 中打开，将无法使用下列功能。
B6: 轻微保真损失 | E6: 发生次数 | F6: 版本
B8: 筛选此工作簿中的某些数据时使用了两个以上条件。在早期版本的 Excel 中，根据该筛选隐藏的行将保持为隐藏，但筛选本身将无法正常显示。 | E8: 1
E9: Sheet1'!A1:Z3097 | F9: Excel 97-2003
B11: 所选文件格式不支持此工作簿中某些单元格或样式包含的格式。这些格式将被转换为最相近的可用格式。 | E11: 8 | F11: Excel 97-2003
